{
"meta":{"test_sets":[],"test_metrics":[],"learn_metrics":[{"best_value":"Min","name":"MultiClass"}],"launch_mode":"Train","parameters":"","iteration_count":1000,"learn_sets":["learn"],"name":"experiment"},
"iterations":[
{"learn":[1.361574156],"iteration":0,"passed_time":0.1498019714,"remaining_time":149.6521694},
{"learn":[1.337311471],"iteration":1,"passed_time":0.1551178828,"remaining_time":77.40382353},
{"learn":[1.316893152],"iteration":2,"passed_time":0.1589988559,"remaining_time":52.84061976},
{"learn":[1.294158146],"iteration":3,"passed_time":0.1635543476,"remaining_time":40.72503254},
{"learn":[1.265425636],"iteration":4,"passed_time":0.1676002789,"remaining_time":33.35245549},
{"learn":[1.228575925],"iteration":5,"passed_time":0.1714407947,"remaining_time":28.40202499},
{"learn":[1.207788685],"iteration":6,"passed_time":0.1746081198,"remaining_time":24.76940899},
{"learn":[1.188951325],"iteration":7,"passed_time":0.1784577351,"remaining_time":22.12875915},
{"learn":[1.159213979],"iteration":8,"passed_time":0.1813546777,"remaining_time":19.96916507},
{"learn":[1.138580038],"iteration":9,"passed_time":0.1841351674,"remaining_time":18.22938157},
{"learn":[1.119356606],"iteration":10,"passed_time":0.1865372103,"remaining_time":16.771391},
{"learn":[1.090968616],"iteration":11,"passed_time":0.1891928168,"remaining_time":15.57687525},
{"learn":[1.06943211],"iteration":12,"passed_time":0.1917685838,"remaining_time":14.55966094},
{"learn":[1.038110249],"iteration":13,"passed_time":0.194152941,"remaining_time":13.67391427},
{"learn":[1.022593644],"iteration":14,"passed_time":0.1965848794,"remaining_time":12.90907375},
{"learn":[0.9961231918],"iteration":15,"passed_time":0.1989518604,"remaining_time":12.23553942},
{"learn":[0.981918558],"iteration":16,"passed_time":0.2010537191,"remaining_time":11.62563564},
{"learn":[0.964891169],"iteration":17,"passed_time":0.203150729,"remaining_time":11.08300088},
{"learn":[0.9514350911],"iteration":18,"passed_time":0.2052256077,"remaining_time":10.59612217},
{"learn":[0.933078785],"iteration":19,"passed_time":0.2072167833,"remaining_time":10.15362238},
{"learn":[0.9210214652],"iteration":20,"passed_time":0.2091691475,"remaining_time":9.751266446},
{"learn":[0.9081318259],"iteration":21,"passed_time":0.2110733807,"remaining_time":9.383171198},
{"learn":[0.895518505],"iteration":22,"passed_time":0.213033648,"remaining_time":9.049298873},
{"learn":[0.8847894771],"iteration":23,"passed_time":0.2148077567,"remaining_time":8.735515441},
{"learn":[0.8733296359],"iteration":24,"passed_time":0.2167508643,"remaining_time":8.453283708},
{"learn":[0.8585868197],"iteration":25,"passed_time":0.2186844106,"remaining_time":8.192254458},
{"learn":[0.842548068],"iteration":26,"passed_time":0.2207335057,"remaining_time":7.954581519},
{"learn":[0.8281840176],"iteration":27,"passed_time":0.2227050618,"remaining_time":7.731047146},
{"learn":[0.8157629916],"iteration":28,"passed_time":0.2245535458,"remaining_time":7.518672171},
{"learn":[0.8053313816],"iteration":29,"passed_time":0.2263638571,"remaining_time":7.319098045},
{"learn":[0.794988984],"iteration":30,"passed_time":0.2282410594,"remaining_time":7.134373761},
{"learn":[0.7846584634],"iteration":31,"passed_time":0.2300041435,"remaining_time":6.95762534},
{"learn":[0.773459228],"iteration":32,"passed_time":0.2319448856,"remaining_time":6.796688011},
{"learn":[0.7649382885],"iteration":33,"passed_time":0.2338948474,"remaining_time":6.64536537},
{"learn":[0.7570680352],"iteration":34,"passed_time":0.2360505707,"remaining_time":6.508251449},
{"learn":[0.7456870612],"iteration":35,"passed_time":0.2382446971,"remaining_time":6.379663557},
{"learn":[0.7364928679],"iteration":36,"passed_time":0.240266619,"remaining_time":6.253425786},
{"learn":[0.7252543294],"iteration":37,"passed_time":0.242221058,"remaining_time":6.13201731},
{"learn":[0.7152770517],"iteration":38,"passed_time":0.2441109008,"remaining_time":6.015142965},
{"learn":[0.7059952953],"iteration":39,"passed_time":0.246062512,"remaining_time":5.905500288},
{"learn":[0.6908490835],"iteration":40,"passed_time":0.2479603758,"remaining_time":5.799853667},
{"learn":[0.6833172661],"iteration":41,"passed_time":0.2496868467,"remaining_time":5.695238076},
{"learn":[0.675710415],"iteration":42,"passed_time":0.2515331328,"remaining_time":5.598074607},
{"learn":[0.6676013446],"iteration":43,"passed_time":0.2535594195,"remaining_time":5.509154661},
{"learn":[0.6591644158],"iteration":44,"passed_time":0.2553577848,"remaining_time":5.419259655},
{"learn":[0.6500376669],"iteration":45,"passed_time":0.2571478224,"remaining_time":5.333022229},
{"learn":[0.6432134928],"iteration":46,"passed_time":0.2589647538,"remaining_time":5.250923624},
{"learn":[0.6369970493],"iteration":47,"passed_time":0.2607841063,"remaining_time":5.172218109},
{"learn":[0.6298848553],"iteration":48,"passed_time":0.2625807949,"remaining_time":5.096210938},
{"learn":[0.616964175],"iteration":49,"passed_time":0.2644256693,"remaining_time":5.024087717},
{"learn":[0.6121347911],"iteration":50,"passed_time":0.2662059688,"remaining_time":4.95351891},
{"learn":[0.6028669719],"iteration":51,"passed_time":0.26816256,"remaining_time":4.888809747},
{"learn":[0.5974770725],"iteration":52,"passed_time":0.2699567684,"remaining_time":4.823567163},
{"learn":[0.5892673432],"iteration":53,"passed_time":0.2718690848,"remaining_time":4.762743596},
{"learn":[0.5798438452],"iteration":54,"passed_time":0.2736990551,"remaining_time":4.702647401},
{"learn":[0.5688416286],"iteration":55,"passed_time":0.2755232481,"remaining_time":4.644534753},
{"learn":[0.5586203272],"iteration":56,"passed_time":0.2773582492,"remaining_time":4.588575948},
{"learn":[0.5535144333],"iteration":57,"passed_time":0.2793832863,"remaining_time":4.537569926},
{"learn":[0.5480603182],"iteration":58,"passed_time":0.2812761761,"remaining_time":4.48611664},
{"learn":[0.5429566379],"iteration":59,"passed_time":0.2831680989,"remaining_time":4.436300217},
{"learn":[0.5350274795],"iteration":60,"passed_time":0.2849435857,"remaining_time":4.386262737},
{"learn":[0.5284756691],"iteration":61,"passed_time":0.2867504574,"remaining_time":4.33825692},
{"learn":[0.5240500273],"iteration":62,"passed_time":0.2885383609,"remaining_time":4.291435621},
{"learn":[0.5180399905],"iteration":63,"passed_time":0.2902987018,"remaining_time":4.245618513},
{"learn":[0.5113050389],"iteration":64,"passed_time":0.2923254941,"remaining_time":4.204989799},
{"learn":[0.5041367134],"iteration":65,"passed_time":0.2943390445,"remaining_time":4.165343449},
{"learn":[0.4981004937],"iteration":66,"passed_time":0.2962886904,"remaining_time":4.12593057},
{"learn":[0.4917005538],"iteration":67,"passed_time":0.2985649962,"remaining_time":4.092096712},
{"learn":[0.4866459608],"iteration":68,"passed_time":0.3005146397,"remaining_time":4.054769993},
{"learn":[0.4784299251],"iteration":69,"passed_time":0.3026182528,"remaining_time":4.020499644},
{"learn":[0.472913365],"iteration":70,"passed_time":0.3045808286,"remaining_time":3.985289997},
{"learn":[0.4700176845],"iteration":71,"passed_time":0.3067077709,"remaining_time":3.953122381},
{"learn":[0.4649269213],"iteration":72,"passed_time":0.30857541,"remaining_time":3.918485001},
{"learn":[0.4605766448],"iteration":73,"passed_time":0.310406703,"remaining_time":3.884278472},
{"learn":[0.4538745341],"iteration":74,"passed_time":0.3125373097,"remaining_time":3.85462682},
{"learn":[0.4492510594],"iteration":75,"passed_time":0.3149405843,"remaining_time":3.829014472},
{"learn":[0.4455572297],"iteration":76,"passed_time":0.31692043,"remaining_time":3.798929311},
{"learn":[0.4398775814],"iteration":77,"passed_time":0.3189812025,"remaining_time":3.770521394},
{"learn":[0.4337313018],"iteration":78,"passed_time":0.3210911651,"remaining_time":3.743353963},
{"learn":[0.4292355142],"iteration":79,"passed_time":0.3232100793,"remaining_time":3.716915912},
{"learn":[0.4248476543],"iteration":80,"passed_time":0.3255505903,"remaining_time":3.6935925},
{"learn":[0.4204495672],"iteration":81,"passed_time":0.3275905579,"remaining_time":3.667416245},
{"learn":[0.4153390983],"iteration":82,"passed_time":0.3297726064,"remaining_time":3.643391326},
{"learn":[0.4108694734],"iteration":83,"passed_time":0.3317029148,"remaining_time":3.617141309},
{"learn":[0.4068337451],"iteration":84,"passed_time":0.3337198471,"remaining_time":3.592396001},
{"learn":[0.4016009648],"iteration":85,"passed_time":0.3354951285,"remaining_time":3.565611017},
{"learn":[0.3980001587],"iteration":86,"passed_time":0.3373738929,"remaining_time":3.540486945},
{"learn":[0.3942412089],"iteration":87,"passed_time":0.3395322322,"remaining_time":3.518788589},
{"learn":[0.3880196374],"iteration":88,"passed_time":0.3414097128,"remaining_time":3.494654476},
{"learn":[0.3838495524],"iteration":89,"passed_time":0.3432630224,"remaining_time":3.470770559},
{"learn":[0.3767436789],"iteration":90,"passed_time":0.3453453166,"remaining_time":3.449658163},
{"learn":[0.3729985986],"iteration":91,"passed_time":0.3472916921,"remaining_time":3.427618005},
{"learn":[0.3667343228],"iteration":92,"passed_time":0.3491670114,"remaining_time":3.405316982},
{"learn":[0.3639887364],"iteration":93,"passed_time":0.3510474288,"remaining_time":3.383499686},
{"learn":[0.3598479157],"iteration":94,"passed_time":0.3528836503,"remaining_time":3.36168109},
{"learn":[0.3558571131],"iteration":95,"passed_time":0.3546829345,"remaining_time":3.339930967},
{"learn":[0.3516917592],"iteration":96,"passed_time":0.3564222821,"remaining_time":3.318034234},
{"learn":[0.3484910544],"iteration":97,"passed_time":0.3580432695,"remaining_time":3.295459481},
{"learn":[0.343763755],"iteration":98,"passed_time":0.3600393909,"remaining_time":3.276722133},
{"learn":[0.3399585396],"iteration":99,"passed_time":0.3618764817,"remaining_time":3.256888335},
{"learn":[0.3352651484],"iteration":100,"passed_time":0.3636816836,"remaining_time":3.237127065},
{"learn":[0.3321589424],"iteration":101,"passed_time":0.3654766838,"remaining_time":3.21762806},
{"learn":[0.3279613929],"iteration":102,"passed_time":0.3673398365,"remaining_time":3.199066343},
{"learn":[0.323729923],"iteration":103,"passed_time":0.3691307746,"remaining_time":3.180203596},
{"learn":[0.3203917912],"iteration":104,"passed_time":0.3708528763,"remaining_time":3.161079279},
{"learn":[0.31736817],"iteration":105,"passed_time":0.3727143651,"remaining_time":3.143458891},
{"learn":[0.3135122947],"iteration":106,"passed_time":0.37484691,"remaining_time":3.128395239},
{"learn":[0.3107002532],"iteration":107,"passed_time":0.3766831115,"remaining_time":3.111123477},
{"learn":[0.3078085583],"iteration":108,"passed_time":0.3784203867,"remaining_time":3.09332628},
{"learn":[0.3046915483],"iteration":109,"passed_time":0.3805192853,"remaining_time":3.078746945},
{"learn":[0.3021067536],"iteration":110,"passed_time":0.3826171296,"remaining_time":3.064384038},
{"learn":[0.2992680804],"iteration":111,"passed_time":0.3845861029,"remaining_time":3.049218388},
{"learn":[0.2963509929],"iteration":112,"passed_time":0.3864229195,"remaining_time":3.033248935},
{"learn":[0.2923113973],"iteration":113,"passed_time":0.3882092577,"remaining_time":3.017135108},
{"learn":[0.2899784643],"iteration":114,"passed_time":0.3901049661,"remaining_time":3.00211213},
{"learn":[0.2857663221],"iteration":115,"passed_time":0.3920551797,"remaining_time":2.987730852},
{"learn":[0.283147068],"iteration":116,"passed_time":0.3939420124,"remaining_time":2.973083734},
{"learn":[0.2807103168],"iteration":117,"passed_time":0.3958519717,"remaining_time":2.958825754},
{"learn":[0.2781649513],"iteration":118,"passed_time":0.3979325476,"remaining_time":2.94603844},
{"learn":[0.2751434981],"iteration":119,"passed_time":0.3998742515,"remaining_time":2.932411178},
{"learn":[0.2727359456],"iteration":120,"passed_time":0.4019123547,"remaining_time":2.919677354},
{"learn":[0.2703056561],"iteration":121,"passed_time":0.403739023,"remaining_time":2.905597231},
{"learn":[0.2675955205],"iteration":122,"passed_time":0.4056806207,"remaining_time":2.892535808},
{"learn":[0.2655724004],"iteration":123,"passed_time":0.4076494346,"remaining_time":2.879846005},
{"learn":[0.2632578295],"iteration":124,"passed_time":0.4095033515,"remaining_time":2.86652346},
{"learn":[0.2606256476],"iteration":125,"passed_time":0.411302106,"remaining_time":2.853000323},
{"learn":[0.2584355382],"iteration":126,"passed_time":0.4131326196,"remaining_time":2.839880133},
{"learn":[0.2565563029],"iteration":127,"passed_time":0.4148853377,"remaining_time":2.826406363},
{"learn":[0.2545527473],"iteration":128,"passed_time":0.416786987,"remaining_time":2.814119889},
{"learn":[0.2518227551],"iteration":129,"passed_time":0.4184473631,"remaining_time":2.800378507},
{"learn":[0.2495861213],"iteration":130,"passed_time":0.4203311407,"remaining_time":2.788303521},
{"learn":[0.2469475791],"iteration":131,"passed_time":0.422046601,"remaining_time":2.775276134},
{"learn":[0.2448072544],"iteration":132,"passed_time":0.4238998139,"remaining_time":2.763316832},
{"learn":[0.2429577174],"iteration":133,"passed_time":0.4256402576,"remaining_time":2.750779575},
{"learn":[0.2405399396],"iteration":134,"passed_time":0.4273839216,"remaining_time":2.738422905},
{"learn":[0.2383250209],"iteration":135,"passed_time":0.4292265736,"remaining_time":2.726851174},
{"learn":[0.2360480776],"iteration":136,"passed_time":0.4311479798,"remaining_time":2.715917566},
{"learn":[0.2343781628],"iteration":137,"passed_time":0.432876783,"remaining_time":2.7039115},
{"learn":[0.2322457502],"iteration":138,"passed_time":0.4347159346,"remaining_time":2.692736832},
{"learn":[0.2304915679],"iteration":139,"passed_time":0.4366027175,"remaining_time":2.681988122},
{"learn":[0.2281937803],"iteration":140,"passed_time":0.4384927531,"remaining_time":2.671384929},
{"learn":[0.2265451848],"iteration":141,"passed_time":0.4402626317,"remaining_time":2.660178437},
{"learn":[0.2234745861],"iteration":142,"passed_time":0.442002828,"remaining_time":2.648926039},
{"learn":[0.2210982202],"iteration":143,"passed_time":0.4437728088,"remaining_time":2.637982808},
{"learn":[0.2194183998],"iteration":144,"passed_time":0.4454448379,"remaining_time":2.626588527},
{"learn":[0.2173235379],"iteration":145,"passed_time":0.4473956529,"remaining_time":2.616958134},
{"learn":[0.2153146067],"iteration":146,"passed_time":0.4492827161,"remaining_time":2.607062291},
{"learn":[0.2132615999],"iteration":147,"passed_time":0.451132406,"remaining_time":2.597059527},
{"learn":[0.2114084304],"iteration":148,"passed_time":0.4531898641,"remaining_time":2.588352848},
{"learn":[0.2092995661],"iteration":149,"passed_time":0.4549488976,"remaining_time":2.578043753},
{"learn":[0.207944652],"iteration":150,"passed_time":0.4566741405,"remaining_time":2.567657916},
{"learn":[0.2065092183],"iteration":151,"passed_time":0.4584611182,"remaining_time":2.557730449},
{"learn":[0.2048008049],"iteration":152,"passed_time":0.4602028072,"remaining_time":2.547658678},
{"learn":[0.203131118],"iteration":153,"passed_time":0.4619906136,"remaining_time":2.537948436},
{"learn":[0.2012997484],"iteration":154,"passed_time":0.4636804254,"remaining_time":2.52780619},
{"learn":[0.1999053348],"iteration":155,"passed_time":0.465499173,"remaining_time":2.518469885},
{"learn":[0.19853455],"iteration":156,"passed_time":0.4673016426,"remaining_time":2.509141941},
{"learn":[0.1965202369],"iteration":157,"passed_time":0.468954796,"remaining_time":2.499113533},
{"learn":[0.1950465998],"iteration":158,"passed_time":0.4706264711,"remaining_time":2.489288441},
{"learn":[0.1935038789],"iteration":159,"passed_time":0.4725420249,"remaining_time":2.480845631},
{"learn":[0.1923318458],"iteration":160,"passed_time":0.4742211889,"remaining_time":2.471252034},
{"learn":[0.1910872721],"iteration":161,"passed_time":0.4760784804,"remaining_time":2.462677572},
{"learn":[0.1896657593],"iteration":162,"passed_time":0.4778325749,"remaining_time":2.453655615},
{"learn":[0.1880939391],"iteration":163,"passed_time":0.4794469667,"remaining_time":2.444010147},
{"learn":[0.1867331165],"iteration":164,"passed_time":0.4811309478,"remaining_time":2.43481419},
{"learn":[0.1858470241],"iteration":165,"passed_time":0.4828337878,"remaining_time":2.425803488},
{"learn":[0.1846999316],"iteration":166,"passed_time":0.4844151953,"remaining_time":2.416274597},
{"learn":[0.1834114999],"iteration":167,"passed_time":0.4861244717,"remaining_time":2.407473574},
{"learn":[0.1822574703],"iteration":168,"passed_time":0.4876370492,"remaining_time":2.397789278},
{"learn":[0.1811975608],"iteration":169,"passed_time":0.4893954092,"remaining_time":2.389401115},
{"learn":[0.1800006233],"iteration":170,"passed_time":0.4911703102,"remaining_time":2.381170685},
{"learn":[0.1785794824],"iteration":171,"passed_time":0.4929375583,"remaining_time":2.372978478},
{"learn":[0.1773699406],"iteration":172,"passed_time":0.4946925095,"remaining_time":2.364801765},
{"learn":[0.1765158969],"iteration":173,"passed_time":0.4964425907,"remaining_time":2.356675747},
{"learn":[0.1754518278],"iteration":174,"passed_time":0.4983996357,"remaining_time":2.349598283},
{"learn":[0.1742711835],"iteration":175,"passed_time":0.500141904,"remaining_time":2.34157346},
{"learn":[0.1732266877],"iteration":176,"passed_time":0.5020308054,"remaining_time":2.334301429},
{"learn":[0.1720377053],"iteration":177,"passed_time":0.5037680301,"remaining_time":2.326389442},
{"learn":[0.1705736098],"iteration":178,"passed_time":0.5055815484,"remaining_time":2.318896376},
{"learn":[0.1695668061],"iteration":179,"passed_time":0.5074842902,"remaining_time":2.311872878},
{"learn":[0.1677569128],"iteration":180,"passed_time":0.5094734379,"remaining_time":2.305296937},
{"learn":[0.1667878462],"iteration":181,"passed_time":0.5112904137,"remaining_time":2.297997574},
{"learn":[0.1660131066],"iteration":182,"passed_time":0.5135523559,"remaining_time":2.292744671},
{"learn":[0.1649571658],"iteration":183,"passed_time":0.5154160426,"remaining_time":2.285758102},
{"learn":[0.1638444113],"iteration":184,"passed_time":0.5172202184,"remaining_time":2.278564746},
{"learn":[0.1629472538],"iteration":185,"passed_time":0.5190546395,"remaining_time":2.271561702},
{"learn":[0.1621745723],"iteration":186,"passed_time":0.5206796562,"remaining_time":2.263703532},
{"learn":[0.1612114144],"iteration":187,"passed_time":0.5223370014,"remaining_time":2.256051304},
{"learn":[0.1601184157],"iteration":188,"passed_time":0.5239965396,"remaining_time":2.248471924},
{"learn":[0.1593525452],"iteration":189,"passed_time":0.5247889533,"remaining_time":2.237258169},
{"learn":[0.1583133799],"iteration":190,"passed_time":0.5263696949,"remaining_time":2.229492582},
{"learn":[0.1574451945],"iteration":191,"passed_time":0.5280722898,"remaining_time":2.22230422},
{"learn":[0.1565667028],"iteration":192,"passed_time":0.5297175887,"remaining_time":2.21493313},
{"learn":[0.1556937092],"iteration":193,"passed_time":0.5315182854,"remaining_time":2.208266691},
{"learn":[0.1546384509],"iteration":194,"passed_time":0.5332089688,"remaining_time":2.201195999},
{"learn":[0.1538214297],"iteration":195,"passed_time":0.5349473906,"remaining_time":2.194376031},
{"learn":[0.153247626],"iteration":196,"passed_time":0.5367956148,"remaining_time":2.188055222},
{"learn":[0.1523971878],"iteration":197,"passed_time":0.5386108719,"remaining_time":2.181646057},
{"learn":[0.1515687372],"iteration":198,"passed_time":0.5402960995,"remaining_time":2.174759677},
{"learn":[0.1506283801],"iteration":199,"passed_time":0.5421716564,"remaining_time":2.168686626},
{"learn":[0.1493342142],"iteration":200,"passed_time":0.5439131582,"remaining_time":2.162122455},
{"learn":[0.1484662381],"iteration":201,"passed_time":0.5456143615,"remaining_time":2.155446834},
{"learn":[0.1476560172],"iteration":202,"passed_time":0.5466224332,"remaining_time":2.146098913},
{"learn":[0.1468677706],"iteration":203,"passed_time":0.5482529142,"remaining_time":2.139261371},
{"learn":[0.146288175],"iteration":204,"passed_time":0.5500373199,"remaining_time":2.133071558},
{"learn":[0.1456538375],"iteration":205,"passed_time":0.5516871208,"remaining_time":2.126405699},
{"learn":[0.1448925635],"iteration":206,"passed_time":0.5533249424,"remaining_time":2.119742412},
{"learn":[0.1443255763],"iteration":207,"passed_time":0.5551531222,"remaining_time":2.113852273},
{"learn":[0.1432878713],"iteration":208,"passed_time":0.5568937495,"remaining_time":2.107669645},
{"learn":[0.1425297994],"iteration":209,"passed_time":0.5588503463,"remaining_time":2.102341779},
{"learn":[0.1416582902],"iteration":210,"passed_time":0.5607368586,"remaining_time":2.096783798},
{"learn":[0.1404605662],"iteration":211,"passed_time":0.5624472031,"remaining_time":2.090605642},
{"learn":[0.1396392661],"iteration":212,"passed_time":0.5640382697,"remaining_time":2.084028724},
{"learn":[0.1384301087],"iteration":213,"passed_time":0.5656336416,"remaining_time":2.077514216},
{"learn":[0.1380618403],"iteration":214,"passed_time":0.5674360826,"remaining_time":2.071801511},
{"learn":[0.1373070407],"iteration":215,"passed_time":0.5693122735,"remaining_time":2.066392696},
{"learn":[0.136346926],"iteration":216,"passed_time":0.5710502587,"remaining_time":2.060517754},
{"learn":[0.1354914606],"iteration":217,"passed_time":0.5728457401,"remaining_time":2.054887012},
{"learn":[0.1348778054],"iteration":218,"passed_time":0.5747474699,"remaining_time":2.049670201},
{"learn":[0.1342914142],"iteration":219,"passed_time":0.5763686105,"remaining_time":2.04348871},
{"learn":[0.1337061684],"iteration":220,"passed_time":0.5780105685,"remaining_time":2.037421868},
{"learn":[0.1330976904],"iteration":221,"passed_time":0.5796579638,"remaining_time":2.031413945},
{"learn":[0.1324986703],"iteration":222,"passed_time":0.5812786125,"remaining_time":2.025351937},
{"learn":[0.1318486204],"iteration":223,"passed_time":0.5829004431,"remaining_time":2.019333678},
{"learn":[0.1313438286],"iteration":224,"passed_time":0.5846785619,"remaining_time":2.013892824},
{"learn":[0.130244679],"iteration":225,"passed_time":0.5863245411,"remaining_time":2.008031836},
{"learn":[0.1296590311],"iteration":226,"passed_time":0.5879688878,"remaining_time":2.002202424},
{"learn":[0.1289259978],"iteration":227,"passed_time":0.5899259312,"remaining_time":1.997468504},
{"learn":[0.1282751807],"iteration":228,"passed_time":0.5915203825,"remaining_time":1.991538056},
{"learn":[0.1275362581],"iteration":229,"passed_time":0.5931493797,"remaining_time":1.985760967},
{"learn":[0.1269544215],"iteration":230,"passed_time":0.5949933548,"remaining_time":1.980735454},
{"learn":[0.1264976889],"iteration":231,"passed_time":0.5958059279,"remaining_time":1.972323072},
{"learn":[0.1255916369],"iteration":232,"passed_time":0.5974421626,"remaining_time":1.966687291},
{"learn":[0.1249105759],"iteration":233,"passed_time":0.5991501028,"remaining_time":1.961320422},
{"learn":[0.1244711588],"iteration":234,"passed_time":0.6008846055,"remaining_time":1.956071163},
{"learn":[0.1238748088],"iteration":235,"passed_time":0.6025538173,"remaining_time":1.950640324},
{"learn":[0.1231443057],"iteration":236,"passed_time":0.6042187023,"remaining_time":1.945227299},
{"learn":[0.1219968556],"iteration":237,"passed_time":0.6062144953,"remaining_time":1.940905233},
{"learn":[0.1215508337],"iteration":238,"passed_time":0.6080082828,"remaining_time":1.935959428},
{"learn":[0.1208568532],"iteration":239,"passed_time":0.6097656175,"remaining_time":1.930924455},
{"learn":[0.1202385752],"iteration":240,"passed_time":0.6115975368,"remaining_time":1.926151578},
{"learn":[0.1194204024],"iteration":241,"passed_time":0.6132957143,"remaining_time":1.920984097},
{"learn":[0.118819427],"iteration":242,"passed_time":0.6149852904,"remaining_time":1.915818374},
{"learn":[0.1181889859],"iteration":243,"passed_time":0.6166260692,"remaining_time":1.910529952},
{"learn":[0.1176036482],"iteration":244,"passed_time":0.6182855673,"remaining_time":1.905328993},
{"learn":[0.1169591479],"iteration":245,"passed_time":0.6201160007,"remaining_time":1.90068075},
{"learn":[0.1164283895],"iteration":246,"passed_time":0.6218403239,"remaining_time":1.895731838},
{"learn":[0.1159096259],"iteration":247,"passed_time":0.6236678603,"remaining_time":1.891121899},
{"learn":[0.1153733136],"iteration":248,"passed_time":0.6253000047,"remaining_time":1.885944994},
{"learn":[0.1147655857],"iteration":249,"passed_time":0.6269757744,"remaining_time":1.880927323},
{"learn":[0.1141289165],"iteration":250,"passed_time":0.6287256728,"remaining_time":1.876157486},
{"learn":[0.1136574114],"iteration":251,"passed_time":0.6304938879,"remaining_time":1.871465985},
{"learn":[0.1128514445],"iteration":252,"passed_time":0.6322020261,"remaining_time":1.866620212},
{"learn":[0.1124309826],"iteration":253,"passed_time":0.6337604144,"remaining_time":1.861359327},
{"learn":[0.1119907946],"iteration":254,"passed_time":0.6354470348,"remaining_time":1.856502121},
{"learn":[0.1114850101],"iteration":255,"passed_time":0.6375117613,"remaining_time":1.852768556},
{"learn":[0.1110878086],"iteration":256,"passed_time":0.6391930237,"remaining_time":1.847939364},
{"learn":[0.1107713607],"iteration":257,"passed_time":0.6402252652,"remaining_time":1.841268011},
{"learn":[0.1103153225],"iteration":258,"passed_time":0.641853987,"remaining_time":1.836346735},
{"learn":[0.1096784808],"iteration":259,"passed_time":0.6435730625,"remaining_time":1.831707947},
{"learn":[0.1092148441],"iteration":260,"passed_time":0.6452970786,"remaining_time":1.827105521},
{"learn":[0.1087058776],"iteration":261,"passed_time":0.6468388877,"remaining_time":1.822011829},
{"learn":[0.1082330064],"iteration":262,"passed_time":0.6485267971,"remaining_time":1.817354561},
{"learn":[0.1077683363],"iteration":263,"passed_time":0.650265059,"remaining_time":1.812860164},
{"learn":[0.1073365794],"iteration":264,"passed_time":0.6520821936,"remaining_time":1.80860533},
{"learn":[0.1069381227],"iteration":265,"passed_time":0.6538576972,"remaining_time":1.804253946},
{"learn":[0.1067671441],"iteration":266,"passed_time":0.6556459611,"remaining_time":1.799956889},
{"learn":[0.1062832283],"iteration":267,"passed_time":0.6575487599,"remaining_time":1.795991389},
{"learn":[0.1058279903],"iteration":268,"passed_time":0.6593335525,"remaining_time":1.791720546},
{"learn":[0.1055015945],"iteration":269,"passed_time":0.6610909434,"remaining_time":1.787394032},
{"learn":[0.1050297496],"iteration":270,"passed_time":0.662860296,"remaining_time":1.783118656},
{"learn":[0.1045626729],"iteration":271,"passed_time":0.6645863267,"remaining_time":1.778745757},
{"learn":[0.1040373729],"iteration":272,"passed_time":0.6656893945,"remaining_time":1.772733296},
{"learn":[0.1038107198],"iteration":273,"passed_time":0.6674533305,"remaining_time":1.76850773},
{"learn":[0.1033222847],"iteration":274,"passed_time":0.6691341647,"remaining_time":1.76408098},
{"learn":[0.1027260895],"iteration":275,"passed_time":0.6707903175,"remaining_time":1.759609384},
{"learn":[0.1023405695],"iteration":276,"passed_time":0.6725187703,"remaining_time":1.755346826},
{"learn":[0.1018675418],"iteration":277,"passed_time":0.6742505957,"remaining_time":1.751111259},
{"learn":[0.101272367],"iteration":278,"passed_time":0.6759927489,"remaining_time":1.74692033},
{"learn":[0.1005942432],"iteration":279,"passed_time":0.6777637681,"remaining_time":1.742821118},
{"learn":[0.1003463298],"iteration":280,"passed_time":0.6795299618,"remaining_time":1.73872613},
{"learn":[0.0999431133],"iteration":281,"passed_time":0.6812735784,"remaining_time":1.734590175},
{"learn":[0.09949581752],"iteration":282,"passed_time":0.6830887477,"remaining_time":1.73065241},
{"learn":[0.0989081783],"iteration":283,"passed_time":0.6849203418,"remaining_time":1.726771003},
{"learn":[0.09863674456],"iteration":284,"passed_time":0.6867317264,"remaining_time":1.722853278},
{"learn":[0.09830550784],"iteration":285,"passed_time":0.6884321126,"remaining_time":1.718673176},
{"learn":[0.09780215576],"iteration":286,"passed_time":0.6901725652,"remaining_time":1.714609892},
{"learn":[0.09747511569],"iteration":287,"passed_time":0.6919260683,"remaining_time":1.710595002},
{"learn":[0.0970857911],"iteration":288,"passed_time":0.6935657032,"remaining_time":1.706315623},
{"learn":[0.09659918866],"iteration":289,"passed_time":0.695302385,"remaining_time":1.702292046},
{"learn":[0.09587042559],"iteration":290,"passed_time":0.6971643221,"remaining_time":1.698589362},
{"learn":[0.09539507256],"iteration":291,"passed_time":0.6989862586,"remaining_time":1.694802298},
{"learn":[0.09493770831],"iteration":292,"passed_time":0.7006258283,"remaining_time":1.690588603},
{"learn":[0.09451726084],"iteration":293,"passed_time":0.7023016449,"remaining_time":1.68647946},
{"learn":[0.09415006666],"iteration":294,"passed_time":0.7040162433,"remaining_time":1.682479497},
{"learn":[0.09379610587],"iteration":295,"passed_time":0.7057912717,"remaining_time":1.6786387},
{"learn":[0.09328461309],"iteration":296,"passed_time":0.707579085,"remaining_time":1.674842077},
{"learn":[0.09289522636],"iteration":297,"passed_time":0.7093437583,"remaining_time":1.671004424},
{"learn":[0.0924851273],"iteration":298,"passed_time":0.7109322783,"remaining_time":1.666767649},
{"learn":[0.09169662561],"iteration":299,"passed_time":0.7126036274,"remaining_time":1.662741797},
{"learn":[0.09135289461],"iteration":300,"passed_time":0.714522466,"remaining_time":1.659306325},
{"learn":[0.09105771734],"iteration":301,"passed_time":0.7161073071,"remaining_time":1.655108942},
{"learn":[0.09046828043],"iteration":302,"passed_time":0.7178261821,"remaining_time":1.651237125},
{"learn":[0.08992470424],"iteration":303,"passed_time":0.7196776963,"remaining_time":1.647683147},
{"learn":[0.0893915554],"iteration":304,"passed_time":0.7213058936,"remaining_time":1.643631462},
{"learn":[0.08909916005],"iteration":305,"passed_time":0.7230409721,"remaining_time":1.639838022},
{"learn":[0.08875156109],"iteration":306,"passed_time":0.7247610571,"remaining_time":1.636024145},
{"learn":[0.08849404033],"iteration":307,"passed_time":0.7266129129,"remaining_time":1.632519921},
{"learn":[0.08817084736],"iteration":308,"passed_time":0.7284012185,"remaining_time":1.628884278},
{"learn":[0.08786966824],"iteration":309,"passed_time":0.730022056,"remaining_time":1.624887802},
{"learn":[0.08750729699],"iteration":310,"passed_time":0.7317341982,"remaining_time":1.621108883},
{"learn":[0.0871542666],"iteration":311,"passed_time":0.7334481474,"remaining_time":1.617347197},
{"learn":[0.08679086496],"iteration":312,"passed_time":0.735185405,"remaining_time":1.613649755},
{"learn":[0.08647820325],"iteration":313,"passed_time":0.7369230815,"remaining_time":1.609965713},
{"learn":[0.08607394071],"iteration":314,"passed_time":0.7387489916,"remaining_time":1.606485902},
{"learn":[0.0856968072],"iteration":315,"passed_time":0.7404171494,"remaining_time":1.602675095},
{"learn":[0.0854311508],"iteration":316,"passed_time":0.7422676616,"remaining_time":1.599270703},
{"learn":[0.08508829456],"iteration":317,"passed_time":0.7442248257,"remaining_time":1.596104815},
{"learn":[0.08472937355],"iteration":318,"passed_time":0.746054353,"remaining_time":1.592674026},
{"learn":[0.08445794721],"iteration":319,"passed_time":0.7477164239,"remaining_time":1.588897401},
{"learn":[0.08412770141],"iteration":320,"passed_time":0.749342833,"remaining_time":1.585058516},
{"learn":[0.0838425629],"iteration":321,"passed_time":0.7510203392,"remaining_time":1.581340963},
{"learn":[0.08361668512],"iteration":322,"passed_time":0.7527348489,"remaining_time":1.5777136},
{"learn":[0.08315021534],"iteration":323,"passed_time":0.7548101638,"remaining_time":1.574850836},
{"learn":[0.0829096165],"iteration":324,"passed_time":0.7567282095,"remaining_time":1.571666281},
{"learn":[0.08251864375],"iteration":325,"passed_time":0.7584535065,"remaining_time":1.568090992},
{"learn":[0.08215454435],"iteration":326,"passed_time":0.7601664202,"remaining_time":1.564501531},
{"learn":[0.08187765772],"iteration":327,"passed_time":0.7618473931,"remaining_time":1.560858074},
{"learn":[0.08161895339],"iteration":328,"passed_time":0.7635163756,"remaining_time":1.557202091},
{"learn":[0.08130649543],"iteration":329,"passed_time":0.7652518366,"remaining_time":1.553693123},
{"learn":[0.08102895178],"iteration":330,"passed_time":0.7669552318,"remaining_time":1.550130061},
{"learn":[0.08071610997],"iteration":331,"passed_time":0.7687021116,"remaining_time":1.546665694},
{"learn":[0.08041726222],"iteration":332,"passed_time":0.7703844922,"remaining_time":1.543082451},
{"learn":[0.08028225244],"iteration":333,"passed_time":0.7720694532,"remaining_time":1.539515736},
{"learn":[0.08009480826],"iteration":334,"passed_time":0.7737927436,"remaining_time":1.536036342},
{"learn":[0.07993758486],"iteration":335,"passed_time":0.7756127052,"remaining_time":1.532758441},
{"learn":[0.07964242752],"iteration":336,"passed_time":0.7773303959,"remaining_time":1.52928799},
{"learn":[0.07938546148],"iteration":337,"passed_time":0.778969061,"remaining_time":1.525673131},
{"learn":[0.07911843517],"iteration":338,"passed_time":0.7808829546,"remaining_time":1.522606587},
{"learn":[0.07888513341],"iteration":339,"passed_time":0.7826755461,"remaining_time":1.519311354},
{"learn":[0.07867803553],"iteration":340,"passed_time":0.784328354,"remaining_time":1.515754795},
{"learn":[0.07837052408],"iteration":341,"passed_time":0.7861053061,"remaining_time":1.51244822},
{"learn":[0.07815845026],"iteration":342,"passed_time":0.7879455975,"remaining_time":1.509271888},
{"learn":[0.07765405886],"iteration":343,"passed_time":0.7898170931,"remaining_time":1.506162829},
{"learn":[0.07736748051],"iteration":344,"passed_time":0.7915308699,"remaining_time":1.502761507},
{"learn":[0.07710180492],"iteration":345,"passed_time":0.7930926452,"remaining_time":1.49908263},
{"learn":[0.07682195797],"iteration":346,"passed_time":0.7948727915,"remaining_time":1.495826896},
{"learn":[0.07656812619],"iteration":347,"passed_time":0.7965230872,"remaining_time":1.492336359},
{"learn":[0.07629674909],"iteration":348,"passed_time":0.7981839448,"remaining_time":1.488876069},
{"learn":[0.0759830087],"iteration":349,"passed_time":0.7998050145,"remaining_time":1.48535217},
{"learn":[0.07578005035],"iteration":350,"passed_time":0.8004230156,"remaining_time":1.479984436},
{"learn":[0.07545548925],"iteration":351,"passed_time":0.8021542821,"remaining_time":1.47669311},
{"learn":[0.07524186131],"iteration":352,"passed_time":0.8031663871,"remaining_time":1.4720925},
{"learn":[0.0749452527],"iteration":353,"passed_time":0.8050812269,"remaining_time":1.469159527},
{"learn":[0.07474965811],"iteration":354,"passed_time":0.806801004,"remaining_time":1.46587788},
{"learn":[0.07444686476],"iteration":355,"passed_time":0.8084772997,"remaining_time":1.462526351},
{"learn":[0.07401565032],"iteration":356,"passed_time":0.8100765172,"remaining_time":1.45904538},
{"learn":[0.07378854484],"iteration":357,"passed_time":0.8118087219,"remaining_time":1.455813406},
{"learn":[0.07355029135],"iteration":358,"passed_time":0.8134268419,"remaining_time":1.452386088},
{"learn":[0.07325503875],"iteration":359,"passed_time":0.815604465,"remaining_time":1.449963493},
{"learn":[0.07302270012],"iteration":360,"passed_time":0.8174517374,"remaining_time":1.446957507},
{"learn":[0.07281025504],"iteration":361,"passed_time":0.8191589831,"remaining_time":1.443711136},
{"learn":[0.07257936066],"iteration":362,"passed_time":0.8209549524,"remaining_time":1.440628939},
{"learn":[0.07234509601],"iteration":363,"passed_time":0.8227745151,"remaining_time":1.437595032},
{"learn":[0.07213871886],"iteration":364,"passed_time":0.824534085,"remaining_time":1.434463408},
{"learn":[0.0719317245],"iteration":365,"passed_time":0.8263316147,"remaining_time":1.431405038},
{"learn":[0.07168020097],"iteration":366,"passed_time":0.8280336961,"remaining_time":1.428188909},
{"learn":[0.07143824049],"iteration":367,"passed_time":0.8295871446,"remaining_time":1.424725748},
{"learn":[0.07118884435],"iteration":368,"passed_time":0.831329463,"remaining_time":1.421595911},
{"learn":[0.07083121989],"iteration":369,"passed_time":0.8329630893,"remaining_time":1.418288503},
{"learn":[0.07060145431],"iteration":370,"passed_time":0.8347972878,"remaining_time":1.415330173},
{"learn":[0.07044648246],"iteration":371,"passed_time":0.8364959597,"remaining_time":1.412149093},
{"learn":[0.0701355361],"iteration":372,"passed_time":0.8381827625,"remaining_time":1.408956011},
{"learn":[0.06979431925],"iteration":373,"passed_time":0.8399706516,"remaining_time":1.405940182},
{"learn":[0.06955310974],"iteration":374,"passed_time":0.8417600685,"remaining_time":1.402933448},
{"learn":[0.06929796677],"iteration":375,"passed_time":0.8438268786,"remaining_time":1.400393543},
{"learn":[0.06911593394],"iteration":376,"passed_time":0.8456007841,"remaining_time":1.397372118},
{"learn":[0.06886601548],"iteration":377,"passed_time":0.8474686087,"remaining_time":1.394511838},
{"learn":[0.06860972445],"iteration":378,"passed_time":0.8493506266,"remaining_time":1.391680051},
{"learn":[0.06836351407],"iteration":379,"passed_time":0.8512451771,"remaining_time":1.38887371},
{"learn":[0.06812063082],"iteration":380,"passed_time":0.8529936173,"remaining_time":1.385834775},
{"learn":[0.06793721999],"iteration":381,"passed_time":0.8547080232,"remaining_time":1.382747535},
{"learn":[0.06770140704],"iteration":382,"passed_time":0.8564574705,"remaining_time":1.379723915},
{"learn":[0.06753795852],"iteration":383,"passed_time":0.8582978413,"remaining_time":1.376852787},
{"learn":[0.06734933177],"iteration":384,"passed_time":0.8600487248,"remaining_time":1.373844067},
{"learn":[0.06718935916],"iteration":385,"passed_time":0.8616975241,"remaining_time":1.370679481},
{"learn":[0.06696438243],"iteration":386,"passed_time":0.8635700236,"remaining_time":1.367877066},
{"learn":[0.06677398902],"iteration":387,"passed_time":0.8652376385,"remaining_time":1.364756275},
{"learn":[0.06642795498],"iteration":388,"passed_time":0.8670197959,"remaining_time":1.361822867},
{"learn":[0.06613509667],"iteration":389,"passed_time":0.8687928987,"remaining_time":1.358881201},
{"learn":[0.06592984351],"iteration":390,"passed_time":0.8705962583,"remaining_time":1.355992638},
{"learn":[0.06575457562],"iteration":391,"passed_time":0.8723376903,"remaining_time":1.35301356},
{"learn":[0.06558390046],"iteration":392,"passed_time":0.8741019859,"remaining_time":1.350076095},
{"learn":[0.06542968015],"iteration":393,"passed_time":0.8757654139,"remaining_time":1.346989444},
{"learn":[0.06524469765],"iteration":394,"passed_time":0.8776898996,"remaining_time":1.344309846},
{"learn":[0.06497509796],"iteration":395,"passed_time":0.879726768,"remaining_time":1.341805474},
{"learn":[0.06476883333],"iteration":396,"passed_time":0.8814513883,"remaining_time":1.338829187},
{"learn":[0.06451055635],"iteration":397,"passed_time":0.8831035603,"remaining_time":1.335749606},
{"learn":[0.06437017162],"iteration":398,"passed_time":0.8850197204,"remaining_time":1.333074817},
{"learn":[0.06414890966],"iteration":399,"passed_time":0.8868539153,"remaining_time":1.330280873},
{"learn":[0.06404494716],"iteration":400,"passed_time":0.8885295186,"remaining_time":1.327254817},
{"learn":[0.06383759535],"iteration":401,"passed_time":0.8901830293,"remaining_time":1.324202616},
{"learn":[0.06355893649],"iteration":402,"passed_time":0.8929379106,"remaining_time":1.322788915},
{"learn":[0.06337094845],"iteration":403,"passed_time":0.8949504062,"remaining_time":1.320273372},
{"learn":[0.06320410754],"iteration":404,"passed_time":0.8968058001,"remaining_time":1.317529509},
{"learn":[0.06295556467],"iteration":405,"passed_time":0.898490984,"remaining_time":1.314540996},
{"learn":[0.06262909902],"iteration":406,"passed_time":0.900236109,"remaining_time":1.311646223},
{"learn":[0.06244148993],"iteration":407,"passed_time":0.9019324904,"remaining_time":1.308686359},
{"learn":[0.06219261014],"iteration":408,"passed_time":0.903565253,"remaining_time":1.305640745},
{"learn":[0.06195689685],"iteration":409,"passed_time":0.9053580707,"remaining_time":1.302832346},
{"learn":[0.0617401516],"iteration":410,"passed_time":0.907224035,"remaining_time":1.300133714},
{"learn":[0.06139120589],"iteration":411,"passed_time":0.9089703359,"remaining_time":1.297268343},
{"learn":[0.06119456675],"iteration":412,"passed_time":0.910832394,"remaining_time":1.294572918},
{"learn":[0.06091347089],"iteration":413,"passed_time":0.9126145987,"remaining_time":1.29176849},
{"learn":[0.06065137309],"iteration":414,"passed_time":0.9143959863,"remaining_time":1.288967836},
{"learn":[0.0601695051],"iteration":415,"passed_time":0.9162913595,"remaining_time":1.286332101},
{"learn":[0.05976098988],"iteration":416,"passed_time":0.9179807619,"remaining_time":1.283411953},
{"learn":[0.05962529611],"iteration":417,"passed_time":0.9196673411,"remaining_time":1.280493762},
{"learn":[0.05945066788],"iteration":418,"passed_time":0.9218857369,"remaining_time":1.278318886},
{"learn":[0.05913394723],"iteration":419,"passed_time":0.9240143699,"remaining_time":1.276019844},
{"learn":[0.05886769812],"iteration":420,"passed_time":0.9265730615,"remaining_time":1.27431307},
{"learn":[0.05870468173],"iteration":421,"passed_time":0.9285106859,"remaining_time":1.271751603},
{"learn":[0.05856527256],"iteration":422,"passed_time":0.9304682161,"remaining_time":1.269220238},
{"learn":[0.05839412398],"iteration":423,"passed_time":0.9322242675,"remaining_time":1.266417873},
{"learn":[0.05823666891],"iteration":424,"passed_time":0.9341077844,"remaining_time":1.263792885},
{"learn":[0.05806826776],"iteration":425,"passed_time":0.9359445116,"remaining_time":1.261108333},
{"learn":[0.05792162637],"iteration":426,"passed_time":0.9377400022,"remaining_time":1.258372415},
{"learn":[0.05771183665],"iteration":427,"passed_time":0.939449449,"remaining_time":1.255525899},
{"learn":[0.05748963691],"iteration":428,"passed_time":0.9412667805,"remaining_time":1.252828279},
{"learn":[0.05741192609],"iteration":429,"passed_time":0.9431689715,"remaining_time":1.250247241},
{"learn":[0.05729584178],"iteration":430,"passed_time":0.9448621479,"remaining_time":1.247393416},
{"learn":[0.05710835186],"iteration":431,"passed_time":0.9466698255,"remaining_time":1.244695511},
{"learn":[0.05690602947],"iteration":432,"passed_time":0.9484499589,"remaining_time":1.241965651},
{"learn":[0.05678236685],"iteration":433,"passed_time":0.9503105453,"remaining_time":1.239345089},
{"learn":[0.05664289139],"iteration":434,"passed_time":0.9521428214,"remaining_time":1.236691251},
{"learn":[0.05657824645],"iteration":435,"passed_time":0.9538381215,"remaining_time":1.233863992},
{"learn":[0.05642474754],"iteration":436,"passed_time":0.955546859,"remaining_time":1.231059226},
{"learn":[0.05630918944],"iteration":437,"passed_time":0.9565705384,"remaining_time":1.227380462},
{"learn":[0.05617958665],"iteration":438,"passed_time":0.9583021845,"remaining_time":1.224618509},
{"learn":[0.05605026554],"iteration":439,"passed_time":0.9600003918,"remaining_time":1.22181868},
{"learn":[0.05583233374],"iteration":440,"passed_time":0.96163904,"remaining_time":1.218948352},
{"learn":[0.05566805006],"iteration":441,"passed_time":0.9633189526,"remaining_time":1.216135691},
{"learn":[0.0555260485],"iteration":442,"passed_time":0.9649351056,"remaining_time":1.213247977},
{"learn":[0.05537899029],"iteration":443,"passed_time":0.9665092207,"remaining_time":1.210313348},
{"learn":[0.05522175702],"iteration":444,"passed_time":0.9682062243,"remaining_time":1.2075381},
{"learn":[0.05505567815],"iteration":445,"passed_time":0.9700790971,"remaining_time":1.204986143},
{"learn":[0.0548917505],"iteration":446,"passed_time":0.9718243407,"remaining_time":1.20227933},
{"learn":[0.05477008662],"iteration":447,"passed_time":0.9737806031,"remaining_time":1.199836815},
{"learn":[0.05465130251],"iteration":448,"passed_time":0.9755624169,"remaining_time":1.197182387},
{"learn":[0.05450500489],"iteration":449,"passed_time":0.9773876001,"remaining_time":1.194584845},
{"learn":[0.0543885696],"iteration":450,"passed_time":0.9791792117,"remaining_time":1.191949861},
{"learn":[0.05421957303],"iteration":451,"passed_time":0.981020748,"remaining_time":1.189379137},
{"learn":[0.05411797761],"iteration":452,"passed_time":0.9827342771,"remaining_time":1.186657063},
{"learn":[0.05397392314],"iteration":453,"passed_time":0.9844171485,"remaining_time":1.183902562},
{"learn":[0.0538202343],"iteration":454,"passed_time":0.9861459244,"remaining_time":1.181207756},
{"learn":[0.0537100167],"iteration":455,"passed_time":0.9882348407,"remaining_time":1.178946828},
{"learn":[0.05350272296],"iteration":456,"passed_time":0.989990322,"remaining_time":1.17629047},
{"learn":[0.05331833304],"iteration":457,"passed_time":0.9916826865,"remaining_time":1.173563354},
{"learn":[0.053095457],"iteration":458,"passed_time":0.9933774125,"remaining_time":1.17084353},
{"learn":[0.05297119687],"iteration":459,"passed_time":0.9950000899,"remaining_time":1.168043584},
{"learn":[0.0528166019],"iteration":460,"passed_time":0.9966806519,"remaining_time":1.165316424},
{"learn":[0.05270731496],"iteration":461,"passed_time":0.9987503614,"remaining_time":1.163046958},
{"learn":[0.05262530361],"iteration":462,"passed_time":1.000493096,"remaining_time":1.16039912},
{"learn":[0.05241580716],"iteration":463,"passed_time":1.002417629,"remaining_time":1.157965192},
{"learn":[0.05224634009],"iteration":464,"passed_time":1.004146609,"remaining_time":1.155308464},
{"learn":[0.05211079171],"iteration":465,"passed_time":1.005762404,"remaining_time":1.152526017},
{"learn":[0.05200638312],"iteration":466,"passed_time":1.007506315,"remaining_time":1.149894787},
{"learn":[0.05190635147],"iteration":467,"passed_time":1.009085965,"remaining_time":1.147080627},
{"learn":[0.05178206044],"iteration":468,"passed_time":1.010766228,"remaining_time":1.144385644},
{"learn":[0.05164703706],"iteration":469,"passed_time":1.01230311,"remaining_time":1.141533295},
{"learn":[0.0514728902],"iteration":470,"passed_time":1.013945227,"remaining_time":1.138804725},
{"learn":[0.0513513248],"iteration":471,"passed_time":1.015719069,"remaining_time":1.136228111},
{"learn":[0.05117202008],"iteration":472,"passed_time":1.017672405,"remaining_time":1.133854879},
{"learn":[0.05104445708],"iteration":473,"passed_time":1.019484254,"remaining_time":1.131326408},
{"learn":[0.05093971124],"iteration":474,"passed_time":1.021145363,"remaining_time":1.128634348},
{"learn":[0.0507915432],"iteration":475,"passed_time":1.022795772,"remaining_time":1.125934842},
{"learn":[0.05066277579],"iteration":476,"passed_time":1.024521354,"remaining_time":1.123322155},
{"learn":[0.05055623694],"iteration":477,"passed_time":1.02625764,"remaining_time":1.120724871},
{"learn":[0.05041973173],"iteration":478,"passed_time":1.027907044,"remaining_time":1.118036681},
{"learn":[0.05031298241],"iteration":479,"passed_time":1.029563692,"remaining_time":1.115360667},
{"learn":[0.05019407553],"iteration":480,"passed_time":1.031230927,"remaining_time":1.112700314},
{"learn":[0.05005684762],"iteration":481,"passed_time":1.032921933,"remaining_time":1.11006963},
{"learn":[0.04993920301],"iteration":482,"passed_time":1.03462632,"remaining_time":1.107457158},
{"learn":[0.04988713794],"iteration":483,"passed_time":1.036449583,"remaining_time":1.104975175},
{"learn":[0.04959020484],"iteration":484,"passed_time":1.038176879,"remaining_time":1.102394005},
{"learn":[0.04948855313],"iteration":485,"passed_time":1.040013825,"remaining_time":1.099932317},
{"learn":[0.04940324266],"iteration":486,"passed_time":1.041656872,"remaining_time":1.097268943},
{"learn":[0.04932692163],"iteration":487,"passed_time":1.043361582,"remaining_time":1.094674447},
{"learn":[0.04920027925],"iteration":488,"passed_time":1.044973891,"remaining_time":1.091987031},
{"learn":[0.04902153355],"iteration":489,"passed_time":1.046704128,"remaining_time":1.089426746},
{"learn":[0.04896623866],"iteration":490,"passed_time":1.048334953,"remaining_time":1.086766784},
{"learn":[0.0488318957],"iteration":491,"passed_time":1.050111757,"remaining_time":1.084261733},
{"learn":[0.04872494155],"iteration":492,"passed_time":1.051912212,"remaining_time":1.081783958},
{"learn":[0.04856960887],"iteration":493,"passed_time":1.053590984,"remaining_time":1.079184287},
{"learn":[0.04838717681],"iteration":494,"passed_time":1.055174392,"remaining_time":1.076491046},
{"learn":[0.04831935666],"iteration":495,"passed_time":1.056851646,"remaining_time":1.07389764},
{"learn":[0.0482739654],"iteration":496,"passed_time":1.058735055,"remaining_time":1.071516565},
{"learn":[0.04815277667],"iteration":497,"passed_time":1.060603512,"remaining_time":1.069122416},
{"learn":[0.04802821571],"iteration":498,"passed_time":1.062361691,"remaining_time":1.066619654},
{"learn":[0.04789066849],"iteration":499,"passed_time":1.064067328,"remaining_time":1.064067328},
{"learn":[0.04772262519],"iteration":500,"passed_time":1.065714029,"remaining_time":1.061459681},
{"learn":[0.04759998363],"iteration":501,"passed_time":1.067579513,"remaining_time":1.059072903},
{"learn":[0.04743336563],"iteration":502,"passed_time":1.069548764,"remaining_time":1.056790727},
{"learn":[0.04735028385],"iteration":503,"passed_time":1.071299649,"remaining_time":1.054294893},
{"learn":[0.04725081173],"iteration":504,"passed_time":1.072959866,"remaining_time":1.051713136},
{"learn":[0.04713690023],"iteration":505,"passed_time":1.074636224,"remaining_time":1.04915078},
{"learn":[0.04699092532],"iteration":506,"passed_time":1.076221945,"remaining_time":1.046503785},
{"learn":[0.04688812352],"iteration":507,"passed_time":1.07788163,"remaining_time":1.043932602},
{"learn":[0.04673108676],"iteration":508,"passed_time":1.079459138,"remaining_time":1.04128573},
{"learn":[0.04663933292],"iteration":509,"passed_time":1.081132609,"remaining_time":1.038735252},
{"learn":[0.04647465652],"iteration":510,"passed_time":1.08291829,"remaining_time":1.036295585},
{"learn":[0.04640775676],"iteration":511,"passed_time":1.084572145,"remaining_time":1.033732826},
{"learn":[0.04629096013],"iteration":512,"passed_time":1.086340458,"remaining_time":1.031282267},
{"learn":[0.04616415475],"iteration":513,"passed_time":1.088051044,"remaining_time":1.028779781},
{"learn":[0.04596536159],"iteration":514,"passed_time":1.090001224,"remaining_time":1.026506007},
{"learn":[0.04587236821],"iteration":515,"passed_time":1.091667772,"remaining_time":1.023967445},
{"learn":[0.04570328897],"iteration":516,"passed_time":1.093285742,"remaining_time":1.021386874},
{"learn":[0.04549135575],"iteration":517,"passed_time":1.094983254,"remaining_time":1.018884031},
{"learn":[0.04531812988],"iteration":518,"passed_time":1.09681854,"remaining_time":1.01651198},
{"learn":[0.04521776272],"iteration":519,"passed_time":1.098516606,"remaining_time":1.014015329},
{"learn":[0.04512765781],"iteration":520,"passed_time":1.100127347,"remaining_time":1.011441458},
{"learn":[0.04500474267],"iteration":521,"passed_time":1.101885316,"remaining_time":1.009006094},
{"learn":[0.04494475622],"iteration":522,"passed_time":1.10362529,"remaining_time":1.006556909},
{"learn":[0.04485818771],"iteration":523,"passed_time":1.105441699,"remaining_time":1.004179864},
{"learn":[0.04476180206],"iteration":524,"passed_time":1.10716736,"remaining_time":1.001722849},
{"learn":[0.04467374327],"iteration":525,"passed_time":1.108866475,"remaining_time":0.9992446941},
{"learn":[0.04458501527],"iteration":526,"passed_time":1.11057986,"remaining_time":0.9967823032},
{"learn":[0.04446422788],"iteration":527,"passed_time":1.112693739,"remaining_time":0.9946807666},
{"learn":[0.04440061653],"iteration":528,"passed_time":1.114901373,"remaining_time":0.9926626595},
{"learn":[0.04427646196],"iteration":529,"passed_time":1.116660785,"remaining_time":0.9902463561},
{"learn":[0.04423645638],"iteration":530,"passed_time":1.118358705,"remaining_time":0.9877782156},
{"learn":[0.04409604587],"iteration":531,"passed_time":1.120091585,"remaining_time":0.9853437247},
{"learn":[0.0439828241],"iteration":532,"passed_time":1.121785641,"remaining_time":0.9828778505},
{"learn":[0.04388997384],"iteration":533,"passed_time":1.123430686,"remaining_time":0.9803720968},
{"learn":[0.0437595362],"iteration":534,"passed_time":1.125190398,"remaining_time":0.9779692243},
{"learn":[0.04368308414],"iteration":535,"passed_time":1.126941217,"remaining_time":0.9755610537},
{"learn":[0.04359610276],"iteration":536,"passed_time":1.12870697,"remaining_time":0.9731682067},
{"learn":[0.04353712707],"iteration":537,"passed_time":1.129440632,"remaining_time":0.9698913974},
{"learn":[0.04343834134],"iteration":538,"passed_time":1.130951081,"remaining_time":0.9672884014},
{"learn":[0.04336271486],"iteration":539,"passed_time":1.132444273,"remaining_time":0.9646747507},
{"learn":[0.04326734296],"iteration":540,"passed_time":1.134075782,"remaining_time":0.9621825947},
{"learn":[0.04310215513],"iteration":541,"passed_time":1.135866955,"remaining_time":0.9598285336},
{"learn":[0.04300679185],"iteration":542,"passed_time":1.137522399,"remaining_time":0.9573623133},
{"learn":[0.04293216156],"iteration":543,"passed_time":1.139219864,"remaining_time":0.9549342975},
{"learn":[0.04284721967],"iteration":544,"passed_time":1.140879841,"remaining_time":0.9524776653},
{"learn":[0.04275427637],"iteration":545,"passed_time":1.142838069,"remaining_time":0.9502719471},
{"learn":[0.04263501151],"iteration":546,"passed_time":1.144606556,"remaining_time":0.9479099997},
{"learn":[0.04251955073],"iteration":547,"passed_time":1.146327391,"remaining_time":0.9455109135},
{"learn":[0.04240602706],"iteration":548,"passed_time":1.148221728,"remaining_time":0.9432568296},
{"learn":[0.0423310629],"iteration":549,"passed_time":1.150040026,"remaining_time":0.9409418392},
{"learn":[0.04223982043],"iteration":550,"passed_time":1.151637663,"remaining_time":0.9384488395},
{"learn":[0.042143251],"iteration":551,"passed_time":1.153332393,"remaining_time":0.9360378846},
{"learn":[0.04207237484],"iteration":552,"passed_time":1.155064566,"remaining_time":0.9336597852},
{"learn":[0.0419733964],"iteration":553,"passed_time":1.156922632,"remaining_time":0.9313853681},
{"learn":[0.04183701651],"iteration":554,"passed_time":1.158744031,"remaining_time":0.9290830519},
{"learn":[0.04172582485],"iteration":555,"passed_time":1.160632716,"remaining_time":0.9268361973},
{"learn":[0.04162950195],"iteration":556,"passed_time":1.162344701,"remaining_time":0.9244500944},
{"learn":[0.04151601475],"iteration":557,"passed_time":1.164014385,"remaining_time":0.9220328997},
{"learn":[0.04138993717],"iteration":558,"passed_time":1.165665839,"remaining_time":0.9196039979},
{"learn":[0.041261758],"iteration":559,"passed_time":1.167392263,"remaining_time":0.9172367779},
{"learn":[0.04120417862],"iteration":560,"passed_time":1.169095916,"remaining_time":0.9148540235},
{"learn":[0.04113089079],"iteration":561,"passed_time":1.170736517,"remaining_time":0.9124245449},
{"learn":[0.04107168952],"iteration":562,"passed_time":1.172493956,"remaining_time":0.9100885588},
{"learn":[0.04099611293],"iteration":563,"passed_time":1.174659425,"remaining_time":0.9080700519},
{"learn":[0.04088535085],"iteration":564,"passed_time":1.176542283,"remaining_time":0.9058334393},
{"learn":[0.0407896327],"iteration":565,"passed_time":1.17815635,"remaining_time":0.9033919717},
{"learn":[0.04070733109],"iteration":566,"passed_time":1.179810654,"remaining_time":0.9009841502},
{"learn":[0.04062802359],"iteration":567,"passed_time":1.181674213,"remaining_time":0.8987381336},
{"learn":[0.0405291997],"iteration":568,"passed_time":1.183432035,"remaining_time":0.8964133696},
{"learn":[0.0404314617],"iteration":569,"passed_time":1.185157832,"remaining_time":0.8940664347},
{"learn":[0.04037424523],"iteration":570,"passed_time":1.187010437,"remaining_time":0.8918169481},
{"learn":[0.04031906667],"iteration":571,"passed_time":1.188714062,"remaining_time":0.8894573751},
{"learn":[0.04022437019],"iteration":572,"passed_time":1.190332444,"remaining_time":0.8870365685},
{"learn":[0.04016732334],"iteration":573,"passed_time":1.191978644,"remaining_time":0.8846392025},
{"learn":[0.04008423762],"iteration":574,"passed_time":1.193687392,"remaining_time":0.8822906808},
{"learn":[0.04001017893],"iteration":575,"passed_time":1.195389593,"remaining_time":0.8799395612},
{"learn":[0.03994109354],"iteration":576,"passed_time":1.197096819,"remaining_time":0.8775943748},
{"learn":[0.03986215271],"iteration":577,"passed_time":1.19866565,"remaining_time":0.8751503534},
{"learn":[0.03978228585],"iteration":578,"passed_time":1.200608225,"remaining_time":0.8729811098},
{"learn":[0.03969246786],"iteration":579,"passed_time":1.20233607,"remaining_time":0.8706571541},
{"learn":[0.03962413266],"iteration":580,"passed_time":1.204044678,"remaining_time":0.8683213771},
{"learn":[0.03954006492],"iteration":581,"passed_time":1.205779352,"remaining_time":0.8660064762},
{"learn":[0.03945510057],"iteration":582,"passed_time":1.20749916,"remaining_time":0.8636829323},
{"learn":[0.0393725029],"iteration":583,"passed_time":1.209172424,"remaining_time":0.8613283017},
{"learn":[0.03930277439],"iteration":584,"passed_time":1.210846421,"remaining_time":0.858976521},
{"learn":[0.03919079446],"iteration":585,"passed_time":1.212542885,"remaining_time":0.8566429257},
{"learn":[0.03910448308],"iteration":586,"passed_time":1.214295578,"remaining_time":0.8543510623},
{"learn":[0.03899759953],"iteration":587,"passed_time":1.216045917,"remaining_time":0.852059384},
{"learn":[0.03894330893],"iteration":588,"passed_time":1.21775771,"remaining_time":0.8497426466},
{"learn":[0.03882211394],"iteration":589,"passed_time":1.219527234,"remaining_time":0.847468078},
{"learn":[0.03874067045],"iteration":590,"passed_time":1.221192752,"remaining_time":0.8451232411},
{"learn":[0.03865742969],"iteration":591,"passed_time":1.22289055,"remaining_time":0.8428029467},
{"learn":[0.03857894804],"iteration":592,"passed_time":1.224679772,"remaining_time":0.8405474996},
{"learn":[0.03849661888],"iteration":593,"passed_time":1.226332938,"remaining_time":0.8382006274},
{"learn":[0.0384439801],"iteration":594,"passed_time":1.228198331,"remaining_time":0.8360005444},
{"learn":[0.03837499491],"iteration":595,"passed_time":1.229834026,"remaining_time":0.8336458835},
{"learn":[0.03819936113],"iteration":596,"passed_time":1.231524844,"remaining_time":0.831330841},
{"learn":[0.0381082204],"iteration":597,"passed_time":1.233213835,"remaining_time":0.8290166583},
{"learn":[0.03800082048],"iteration":598,"passed_time":1.235009474,"remaining_time":0.8267759586},
{"learn":[0.03798378536],"iteration":599,"passed_time":1.236791218,"remaining_time":0.8245274784},
{"learn":[0.03793121422],"iteration":600,"passed_time":1.238623637,"remaining_time":0.8223141951},
{"learn":[0.03786606079],"iteration":601,"passed_time":1.240403284,"remaining_time":0.8200672874},
{"learn":[0.03779054026],"iteration":602,"passed_time":1.242007964,"remaining_time":0.8177067359},
{"learn":[0.03772609822],"iteration":603,"passed_time":1.243669178,"remaining_time":0.8153857526},
{"learn":[0.03766727098],"iteration":604,"passed_time":1.245525679,"remaining_time":0.8131944516},
{"learn":[0.03759082539],"iteration":605,"passed_time":1.247282172,"remaining_time":0.8109392339},
{"learn":[0.03750123518],"iteration":606,"passed_time":1.248948358,"remaining_time":0.8086271905},
{"learn":[0.03743366102],"iteration":607,"passed_time":1.25056879,"remaining_time":0.8062877722},
{"learn":[0.03734869749],"iteration":608,"passed_time":1.252373775,"remaining_time":0.8040692055},
{"learn":[0.03726945018],"iteration":609,"passed_time":1.254021163,"remaining_time":0.8017512351},
{"learn":[0.03720003457],"iteration":610,"passed_time":1.255673647,"remaining_time":0.7994387051},
{"learn":[0.03710464342],"iteration":611,"passed_time":1.257226742,"remaining_time":0.7970653202},
{"learn":[0.03703866959],"iteration":612,"passed_time":1.25876299,"remaining_time":0.7946839758},
{"learn":[0.03698140034],"iteration":613,"passed_time":1.260257796,"remaining_time":0.7922793311},
{"learn":[0.03688374954],"iteration":614,"passed_time":1.261722678,"remaining_time":0.7898589121},
{"learn":[0.03679001797],"iteration":615,"passed_time":1.263226058,"remaining_time":0.7874655944},
{"learn":[0.0367187705],"iteration":616,"passed_time":1.264818328,"remaining_time":0.7851303399},
{"learn":[0.03658237411],"iteration":617,"passed_time":1.266446517,"remaining_time":0.7828196916},
{"learn":[0.03649380676],"iteration":618,"passed_time":1.268039026,"remaining_time":0.7804892872},
{"learn":[0.03633435408],"iteration":619,"passed_time":1.269656072,"remaining_time":0.7781763019},
{"learn":[0.03626228479],"iteration":620,"passed_time":1.271287943,"remaining_time":0.7758746063},
{"learn":[0.03620610172],"iteration":621,"passed_time":1.272833214,"remaining_time":0.7735224358},
{"learn":[0.03606935224],"iteration":622,"passed_time":1.274487773,"remaining_time":0.7712389895},
{"learn":[0.03600241431],"iteration":623,"passed_time":1.275990758,"remaining_time":0.7688662258},
{"learn":[0.03594272171],"iteration":624,"passed_time":1.276619582,"remaining_time":0.7659717492},
{"learn":[0.03584369671],"iteration":625,"passed_time":1.278235653,"remaining_time":0.7636743359},
{"learn":[0.0357809712],"iteration":626,"passed_time":1.279835,"remaining_time":0.7613691466},
{"learn":[0.03570878708],"iteration":627,"passed_time":1.281466808,"remaining_time":0.759085434},
{"learn":[0.03564545739],"iteration":628,"passed_time":1.283166007,"remaining_time":0.7568435428},
{"learn":[0.03550349993],"iteration":629,"passed_time":1.284714275,"remaining_time":0.7545147332},
{"learn":[0.03544641156],"iteration":630,"passed_time":1.286426421,"remaining_time":0.7522842301},
{"learn":[0.03532025311],"iteration":631,"passed_time":1.287909999,"remaining_time":0.7499222777},
{"learn":[0.03527578074],"iteration":632,"passed_time":1.289633534,"remaining_time":0.7477022225},
{"learn":[0.03520368494],"iteration":633,"passed_time":1.291386516,"remaining_time":0.7455007332},
{"learn":[0.03512826989],"iteration":634,"passed_time":1.293120948,"remaining_time":0.7432899938},
{"learn":[0.0350548356],"iteration":635,"passed_time":1.294930387,"remaining_time":0.7411236806},
{"learn":[0.03499757739],"iteration":636,"passed_time":1.296940069,"remaining_time":0.7390725981},
{"learn":[0.03493248399],"iteration":637,"passed_time":1.298685825,"remaining_time":0.7368718944},
{"learn":[0.03486247213],"iteration":638,"passed_time":1.300388949,"remaining_time":0.7346485297},
{"learn":[0.03474243867],"iteration":639,"passed_time":1.302040836,"remaining_time":0.73239797},
{"learn":[0.03467168979],"iteration":640,"passed_time":1.303726283,"remaining_time":0.7301680744},
{"learn":[0.03459144056],"iteration":641,"passed_time":1.305389822,"remaining_time":0.7279276575},
{"learn":[0.03452888307],"iteration":642,"passed_time":1.307021325,"remaining_time":0.7256712488},
{"learn":[0.03446144255],"iteration":643,"passed_time":1.308705493,"remaining_time":0.7234458938},
{"learn":[0.03442303345],"iteration":644,"passed_time":1.310378287,"remaining_time":0.7212159562},
{"learn":[0.03434116659],"iteration":645,"passed_time":1.312339113,"remaining_time":0.7191455819},
{"learn":[0.0342711631],"iteration":646,"passed_time":1.314265514,"remaining_time":0.7170567645},
{"learn":[0.0341930967],"iteration":647,"passed_time":1.31613043,"remaining_time":0.7149350484},
{"learn":[0.03414389759],"iteration":648,"passed_time":1.317922174,"remaining_time":0.7127745504},
{"learn":[0.03407471243],"iteration":649,"passed_time":1.319684985,"remaining_time":0.7105996071},
{"learn":[0.03401904812],"iteration":650,"passed_time":1.320815417,"remaining_time":0.7080869134},
{"learn":[0.03394243878],"iteration":651,"passed_time":1.322645787,"remaining_time":0.7059520457},
{"learn":[0.03388565844],"iteration":652,"passed_time":1.324318439,"remaining_time":0.7037343006},
{"learn":[0.03383261151],"iteration":653,"passed_time":1.325962265,"remaining_time":0.7015029721},
{"learn":[0.03377709463],"iteration":654,"passed_time":1.327740614,"remaining_time":0.6993442928},
{"learn":[0.03369346117],"iteration":655,"passed_time":1.32944221,"remaining_time":0.697146525},
{"learn":[0.033632573],"iteration":656,"passed_time":1.33112213,"remaining_time":0.6949389508},
{"learn":[0.03357102446],"iteration":657,"passed_time":1.332833343,"remaining_time":0.692749245},
{"learn":[0.03353358198],"iteration":658,"passed_time":1.334518937,"remaining_time":0.6905477353},
{"learn":[0.03345414214],"iteration":659,"passed_time":1.336240639,"remaining_time":0.6883663896},
{"learn":[0.03339941947],"iteration":660,"passed_time":1.337847717,"remaining_time":0.686127649},
{"learn":[0.03332632928],"iteration":661,"passed_time":1.339571903,"remaining_time":0.6839506092},
{"learn":[0.0332821839],"iteration":662,"passed_time":1.341489786,"remaining_time":0.6818733903},
{"learn":[0.03322924949],"iteration":663,"passed_time":1.343515731,"remaining_time":0.6798513337},
{"learn":[0.03314927303],"iteration":664,"passed_time":1.345267447,"remaining_time":0.6776911201},
{"learn":[0.0330788002],"iteration":665,"passed_time":1.346929764,"remaining_time":0.6754872993},
{"learn":[0.03304189393],"iteration":666,"passed_time":1.348095062,"remaining_time":0.673036965},
{"learn":[0.03297612856],"iteration":667,"passed_time":1.350000177,"remaining_time":0.670958172},
{"learn":[0.03292498865],"iteration":668,"passed_time":1.351755534,"remaining_time":0.6688058025},
{"learn":[0.03286278969],"iteration":669,"passed_time":1.353501374,"remaining_time":0.6666499306},
{"learn":[0.03279998221],"iteration":670,"passed_time":1.355122684,"remaining_time":0.6644342221},
{"learn":[0.0327595639],"iteration":671,"passed_time":1.356814942,"remaining_time":0.6622549123},
{"learn":[0.03271216768],"iteration":672,"passed_time":1.35844683,"remaining_time":0.6600477167},
{"learn":[0.03265465428],"iteration":673,"passed_time":1.360131553,"remaining_time":0.657867784},
{"learn":[0.03258522613],"iteration":674,"passed_time":1.361894937,"remaining_time":0.6557271917},
{"learn":[0.03252531125],"iteration":675,"passed_time":1.363648468,"remaining_time":0.6535829936},
{"learn":[0.03245829956],"iteration":676,"passed_time":1.365320387,"remaining_time":0.6514010118},
{"learn":[0.03239848909],"iteration":677,"passed_time":1.367055099,"remaining_time":0.6492503567},
{"learn":[0.03235065094],"iteration":678,"passed_time":1.3686977,"remaining_time":0.6470573812},
{"learn":[0.03229463623],"iteration":679,"passed_time":1.370369066,"remaining_time":0.6448795604},
{"learn":[0.03221910627],"iteration":680,"passed_time":1.371997983,"remaining_time":0.6426833428},
{"learn":[0.0321433018],"iteration":681,"passed_time":1.373530154,"remaining_time":0.6404436789},
{"learn":[0.03205751593],"iteration":682,"passed_time":1.375253261,"remaining_time":0.6382947051},
{"learn":[0.03202008838],"iteration":683,"passed_time":1.376829231,"remaining_time":0.6360790013},
{"learn":[0.03196311223],"iteration":684,"passed_time":1.378477523,"remaining_time":0.6338984231},
{"learn":[0.03187929428],"iteration":685,"passed_time":1.380164291,"remaining_time":0.631737008},
{"learn":[0.03179570806],"iteration":686,"passed_time":1.38173657,"remaining_time":0.6295248127},
{"learn":[0.03175380257],"iteration":687,"passed_time":1.383401893,"remaining_time":0.6273566725},
{"learn":[0.03170505807],"iteration":688,"passed_time":1.385143104,"remaining_time":0.6252242458},
{"learn":[0.03165858858],"iteration":689,"passed_time":1.386720263,"remaining_time":0.6230192487},
{"learn":[0.03163808714],"iteration":690,"passed_time":1.388190391,"remaining_time":0.6207682069},
{"learn":[0.03158630028],"iteration":691,"passed_time":1.38966698,"remaining_time":0.6185222975},
{"learn":[0.03154892354],"iteration":692,"passed_time":1.391257184,"remaining_time":0.6163289401},
{"learn":[0.03147277989],"iteration":693,"passed_time":1.393069876,"remaining_time":0.6142354206},
{"learn":[0.03141617145],"iteration":694,"passed_time":1.394687221,"remaining_time":0.6120569819},
{"learn":[0.03136230851],"iteration":695,"passed_time":1.39627174,"remaining_time":0.6098658174},
{"learn":[0.03131755677],"iteration":696,"passed_time":1.397858771,"remaining_time":0.6076774858},
{"learn":[0.03126337494],"iteration":697,"passed_time":1.399377604,"remaining_time":0.6054613702},
{"learn":[0.03121205944],"iteration":698,"passed_time":1.400953743,"remaining_time":0.6032719266},
{"learn":[0.031168104],"iteration":699,"passed_time":1.402451792,"remaining_time":0.6010507678},
{"learn":[0.0311167358],"iteration":700,"passed_time":1.404010046,"remaining_time":0.598857352},
{"learn":[0.03104377629],"iteration":701,"passed_time":1.405537975,"remaining_time":0.5966528724},
{"learn":[0.03099586014],"iteration":702,"passed_time":1.407126007,"remaining_time":0.5944757101},
{"learn":[0.0309301651],"iteration":703,"passed_time":1.408681882,"remaining_time":0.5922867003},
{"learn":[0.03089339254],"iteration":704,"passed_time":1.410191371,"remaining_time":0.5900800771},
{"learn":[0.03085148332],"iteration":705,"passed_time":1.411658785,"remaining_time":0.5878579075},
{"learn":[0.03079747765],"iteration":706,"passed_time":1.413197565,"remaining_time":0.5856674492},
{"learn":[0.03076106609],"iteration":707,"passed_time":1.415019579,"remaining_time":0.5835956458},
{"learn":[0.03068499676],"iteration":708,"passed_time":1.416615929,"remaining_time":0.5814319258},
{"learn":[0.03065774837],"iteration":709,"passed_time":1.418100013,"remaining_time":0.579223949},
{"learn":[0.03061257756],"iteration":710,"passed_time":1.419602364,"remaining_time":0.5770254334},
{"learn":[0.03056567427],"iteration":711,"passed_time":1.421307857,"remaining_time":0.5749110432},
{"learn":[0.03052456992],"iteration":712,"passed_time":1.423155069,"remaining_time":0.5728548453},
{"learn":[0.03047263674],"iteration":713,"passed_time":1.42484231,"remaining_time":0.5707351548},
{"learn":[0.03042502796],"iteration":714,"passed_time":1.426592479,"remaining_time":0.5686417574},
{"learn":[0.03038060514],"iteration":715,"passed_time":1.428453347,"remaining_time":0.5665932269},
{"learn":[0.0302873853],"iteration":716,"passed_time":1.430328323,"remaining_time":0.5645507885},
{"learn":[0.03023675392],"iteration":717,"passed_time":1.432091059,"remaining_time":0.5624647334},
{"learn":[0.03020290949],"iteration":718,"passed_time":1.433817441,"remaining_time":0.5603653698},
{"learn":[0.03014343562],"iteration":719,"passed_time":1.435464137,"remaining_time":0.5582360533},
{"learn":[0.03011651776],"iteration":720,"passed_time":1.437004851,"remaining_time":0.5560670643},
{"learn":[0.03007017293],"iteration":721,"passed_time":1.438527675,"remaining_time":0.5538929276},
{"learn":[0.03000929939],"iteration":722,"passed_time":1.4400519,"remaining_time":0.5517211289},
{"learn":[0.02995696993],"iteration":723,"passed_time":1.441665456,"remaining_time":0.549585174},
{"learn":[0.02991566292],"iteration":724,"passed_time":1.443260824,"remaining_time":0.5474437609},
{"learn":[0.02986260012],"iteration":725,"passed_time":1.445878034,"remaining_time":0.5456895059},
{"learn":[0.02980607058],"iteration":726,"passed_time":1.447556929,"remaining_time":0.5435805248},
{"learn":[0.02975910639],"iteration":727,"passed_time":1.449176658,"remaining_time":0.5414506194},
{"learn":[0.02972861234],"iteration":728,"passed_time":1.450692375,"remaining_time":0.539283448},
{"learn":[0.02968840799],"iteration":729,"passed_time":1.452365758,"remaining_time":0.5371763764},
{"learn":[0.02964681319],"iteration":730,"passed_time":1.45396502,"remaining_time":0.5350432154},
{"learn":[0.02958766669],"iteration":731,"passed_time":1.455589933,"remaining_time":0.5329209045},
{"learn":[0.0295380077],"iteration":732,"passed_time":1.457288618,"remaining_time":0.5308268227},
{"learn":[0.02950242031],"iteration":733,"passed_time":1.459012801,"remaining_time":0.5287430585},
{"learn":[0.02946579268],"iteration":734,"passed_time":1.460817723,"remaining_time":0.526689383},
{"learn":[0.02942569802],"iteration":735,"passed_time":1.462297251,"remaining_time":0.5245196662},
{"learn":[0.02936413],"iteration":736,"passed_time":1.463859895,"remaining_time":0.5223814822},
{"learn":[0.0293054855],"iteration":737,"passed_time":1.464435692,"remaining_time":0.519894514},
{"learn":[0.02926706161],"iteration":738,"passed_time":1.465997157,"remaining_time":0.5177608361},
{"learn":[0.02920016038],"iteration":739,"passed_time":1.467702313,"remaining_time":0.5156791911},
{"learn":[0.02910255716],"iteration":740,"passed_time":1.469283283,"remaining_time":0.5135551556},
{"learn":[0.02904886646],"iteration":741,"passed_time":1.470774875,"remaining_time":0.5114015063},
{"learn":[0.02897887819],"iteration":742,"passed_time":1.472356162,"remaining_time":0.5092806644},
{"learn":[0.02891926363],"iteration":743,"passed_time":1.473938844,"remaining_time":0.5071617527},
{"learn":[0.02888016104],"iteration":744,"passed_time":1.4761054,"remaining_time":0.5052441303},
{"learn":[0.02880580067],"iteration":745,"passed_time":1.478089755,"remaining_time":0.5032638041},
{"learn":[0.02876725748],"iteration":746,"passed_time":1.479817197,"remaining_time":0.5011964535},
{"learn":[0.02875270631],"iteration":747,"passed_time":1.481407143,"remaining_time":0.49908369},
{"learn":[0.02869486356],"iteration":748,"passed_time":1.482945975,"remaining_time":0.4969551933},
{"learn":[0.02862908499],"iteration":749,"passed_time":1.484591633,"remaining_time":0.4948638777},
{"learn":[0.02859331138],"iteration":750,"passed_time":1.486261022,"remaining_time":0.4927816173},
{"learn":[0.02853842248],"iteration":751,"passed_time":1.487960707,"remaining_time":0.4907104459},
{"learn":[0.02849379438],"iteration":752,"passed_time":1.489731735,"remaining_time":0.4886636636},
{"learn":[0.02845413068],"iteration":753,"passed_time":1.491382889,"remaining_time":0.4865785021},
{"learn":[0.02841063453],"iteration":754,"passed_time":1.49306299,"remaining_time":0.4845038841},
{"learn":[0.02835117622],"iteration":755,"passed_time":1.494661656,"remaining_time":0.4824040266},
{"learn":[0.02831988308],"iteration":756,"passed_time":1.496193079,"remaining_time":0.4802839078},
{"learn":[0.02827287109],"iteration":757,"passed_time":1.49769577,"remaining_time":0.4781561693},
{"learn":[0.02823345764],"iteration":758,"passed_time":1.499295787,"remaining_time":0.476060981},
{"learn":[0.02818609422],"iteration":759,"passed_time":1.500922523,"remaining_time":0.4739755336},
{"learn":[0.02815435583],"iteration":760,"passed_time":1.502573224,"remaining_time":0.471898818},
{"learn":[0.02810083318],"iteration":761,"passed_time":1.504300398,"remaining_time":0.4698471059},
{"learn":[0.02801702101],"iteration":762,"passed_time":1.505978787,"remaining_time":0.467781091},
{"learn":[0.02797359568],"iteration":763,"passed_time":1.507704422,"remaining_time":0.4657306853},
{"learn":[0.02791858263],"iteration":764,"passed_time":1.50933066,"remaining_time":0.4636505948},
{"learn":[0.02788631024],"iteration":765,"passed_time":1.510964638,"remaining_time":0.4615740541},
{"learn":[0.02784477417],"iteration":766,"passed_time":1.512887027,"remaining_time":0.4595862807},
{"learn":[0.02776786701],"iteration":767,"passed_time":1.514663708,"remaining_time":0.4575546617},
{"learn":[0.02772290247],"iteration":768,"passed_time":1.516239274,"remaining_time":0.455463293},
{"learn":[0.02769092389],"iteration":769,"passed_time":1.517788536,"remaining_time":0.4533654067},
{"learn":[0.02765851766],"iteration":770,"passed_time":1.519890831,"remaining_time":0.4514332039},
{"learn":[0.02762339942],"iteration":771,"passed_time":1.521444095,"remaining_time":0.4493384115},
{"learn":[0.02759192609],"iteration":772,"passed_time":1.523095313,"remaining_time":0.4472737852},
{"learn":[0.02756708121],"iteration":773,"passed_time":1.524744471,"remaining_time":0.4452096258},
{"learn":[0.02751547983],"iteration":774,"passed_time":1.526264271,"remaining_time":0.4431089818},
{"learn":[0.02747138992],"iteration":775,"passed_time":1.527855042,"remaining_time":0.4410303215},
{"learn":[0.02741711725],"iteration":776,"passed_time":1.529362385,"remaining_time":0.4389289727},
{"learn":[0.02734663958],"iteration":777,"passed_time":1.530868211,"remaining_time":0.4368287184},
{"learn":[0.02730078828],"iteration":778,"passed_time":1.532421673,"remaining_time":0.4347435043},
{"learn":[0.02723151287],"iteration":779,"passed_time":1.534248006,"remaining_time":0.4327366171},
{"learn":[0.02720931387],"iteration":780,"passed_time":1.535838402,"remaining_time":0.4306640334},
{"learn":[0.02718328527],"iteration":781,"passed_time":1.537337358,"remaining_time":0.428567192},
{"learn":[0.02714932415],"iteration":782,"passed_time":1.538759415,"remaining_time":0.4264505659},
{"learn":[0.02712378449],"iteration":783,"passed_time":1.540269529,"remaining_time":0.4243599724},
{"learn":[0.02707084879],"iteration":784,"passed_time":1.541927501,"remaining_time":0.4223113537},
{"learn":[0.02702854524],"iteration":785,"passed_time":1.543649096,"remaining_time":0.4202810516},
{"learn":[0.0269707777],"iteration":786,"passed_time":1.545208273,"remaining_time":0.4182075757},
{"learn":[0.02691165101],"iteration":787,"passed_time":1.546700313,"remaining_time":0.4161173432},
{"learn":[0.02686485217],"iteration":788,"passed_time":1.548514176,"remaining_time":0.414114691},
{"learn":[0.02682942817],"iteration":789,"passed_time":1.550014746,"remaining_time":0.4120292362},
{"learn":[0.02678584365],"iteration":790,"passed_time":1.55091176,"remaining_time":0.4097857874},
{"learn":[0.02674820489],"iteration":791,"passed_time":1.552430019,"remaining_time":0.4077088939},
{"learn":[0.02671701583],"iteration":792,"passed_time":1.554008791,"remaining_time":0.4056492053},
{"learn":[0.02669530441],"iteration":793,"passed_time":1.554925342,"remaining_time":0.4034189175},
{"learn":[0.02666103488],"iteration":794,"passed_time":1.55640156,"remaining_time":0.4013362514},
{"learn":[0.02663043584],"iteration":795,"passed_time":1.558030404,"remaining_time":0.3992942241},
{"learn":[0.02659882359],"iteration":796,"passed_time":1.559608662,"remaining_time":0.3972403492},
{"learn":[0.02656635462],"iteration":797,"passed_time":1.561181096,"remaining_time":0.3951861921},
{"learn":[0.0265335957],"iteration":798,"passed_time":1.563497758,"remaining_time":0.3933204623},
{"learn":[0.02648972971],"iteration":799,"passed_time":1.565315711,"remaining_time":0.3913289277},
{"learn":[0.02642073958],"iteration":800,"passed_time":1.56696423,"remaining_time":0.3892957324},
{"learn":[0.02638342781],"iteration":801,"passed_time":1.56879644,"remaining_time":0.3873088469},
{"learn":[0.0263515725],"iteration":802,"passed_time":1.570792105,"remaining_time":0.3853624468},
{"learn":[0.02631954992],"iteration":803,"passed_time":1.572602889,"remaining_time":0.3833708535},
{"learn":[0.02629330025],"iteration":804,"passed_time":1.574267522,"remaining_time":0.3813443065},
{"learn":[0.02625113819],"iteration":805,"passed_time":1.575878692,"remaining_time":0.3793057895},
{"learn":[0.02620731208],"iteration":806,"passed_time":1.577630328,"remaining_time":0.3773019247},
{"learn":[0.02616532978],"iteration":807,"passed_time":1.579328562,"remaining_time":0.375285995},
{"learn":[0.02613647246],"iteration":808,"passed_time":1.581040422,"remaining_time":0.3732740674},
{"learn":[0.02610668766],"iteration":809,"passed_time":1.582717168,"remaining_time":0.3712546443},
{"learn":[0.0260694369],"iteration":810,"passed_time":1.58435293,"remaining_time":0.3692265152},
{"learn":[0.02602813865],"iteration":811,"passed_time":1.586035017,"remaining_time":0.3672100778},
{"learn":[0.02600016265],"iteration":812,"passed_time":1.58763146,"remaining_time":0.3651747639},
{"learn":[0.02593817417],"iteration":813,"passed_time":1.58927587,"remaining_time":0.3631514886},
{"learn":[0.02588418397],"iteration":814,"passed_time":1.590837131,"remaining_time":0.3611102691},
{"learn":[0.02585348207],"iteration":815,"passed_time":1.592367013,"remaining_time":0.35906315},
{"learn":[0.0258260214],"iteration":816,"passed_time":1.593950815,"remaining_time":0.3570293747},
{"learn":[0.02579235396],"iteration":817,"passed_time":1.595512077,"remaining_time":0.3549916846},
{"learn":[0.02575674886],"iteration":818,"passed_time":1.597116834,"remaining_time":0.3529647705},
{"learn":[0.02572461458],"iteration":819,"passed_time":1.598593095,"remaining_time":0.3509106793},
{"learn":[0.02567506126],"iteration":820,"passed_time":1.600120421,"remaining_time":0.3488691296},
{"learn":[0.02562242696],"iteration":821,"passed_time":1.601560817,"remaining_time":0.3468100067},
{"learn":[0.02558305593],"iteration":822,"passed_time":1.603128978,"remaining_time":0.3447798653},
{"learn":[0.02552718928],"iteration":823,"passed_time":1.604756253,"remaining_time":0.3427634715},
{"learn":[0.02549653814],"iteration":824,"passed_time":1.60639714,"remaining_time":0.3407509085},
{"learn":[0.02546163707],"iteration":825,"passed_time":1.607890947,"remaining_time":0.3387082624},
{"learn":[0.02543144912],"iteration":826,"passed_time":1.609359035,"remaining_time":0.3366615635},
{"learn":[0.02536340602],"iteration":827,"passed_time":1.610807414,"remaining_time":0.3346121681},
{"learn":[0.02534125513],"iteration":828,"passed_time":1.61237965,"remaining_time":0.332589771},
{"learn":[0.02531673989],"iteration":829,"passed_time":1.613954328,"remaining_time":0.3305689588},
{"learn":[0.02528904975],"iteration":830,"passed_time":1.61618754,"remaining_time":0.3286831459},
{"learn":[0.02523210053],"iteration":831,"passed_time":1.617752625,"remaining_time":0.3266615878},
{"learn":[0.02520671969],"iteration":832,"passed_time":1.619333483,"remaining_time":0.3246442878},
{"learn":[0.02516484799],"iteration":833,"passed_time":1.620950843,"remaining_time":0.3226352998},
{"learn":[0.02513577144],"iteration":834,"passed_time":1.622504771,"remaining_time":0.3206147152},
{"learn":[0.0251019591],"iteration":835,"passed_time":1.62428343,"remaining_time":0.3186393332},
{"learn":[0.02507021422],"iteration":836,"passed_time":1.62598221,"remaining_time":0.3166488654},
{"learn":[0.02502619596],"iteration":837,"passed_time":1.627766446,"remaining_time":0.3146756137},
{"learn":[0.02499332355],"iteration":838,"passed_time":1.629453266,"remaining_time":0.3126841189},
{"learn":[0.0249525535],"iteration":839,"passed_time":1.631347788,"remaining_time":0.3107329121},
{"learn":[0.0249166035],"iteration":840,"passed_time":1.633006661,"remaining_time":0.3087372878},
{"learn":[0.02488817869],"iteration":841,"passed_time":1.634775052,"remaining_time":0.3067630145},
{"learn":[0.02485410276],"iteration":842,"passed_time":1.636382366,"remaining_time":0.3047592306},
{"learn":[0.02481954246],"iteration":843,"passed_time":1.638121161,"remaining_time":0.3027806885},
{"learn":[0.02479536513],"iteration":844,"passed_time":1.63975561,"remaining_time":0.3007835734},
{"learn":[0.02476990997],"iteration":845,"passed_time":1.641359374,"remaining_time":0.29878173},
{"learn":[0.02471473354],"iteration":846,"passed_time":1.643028371,"remaining_time":0.2967926102},
{"learn":[0.02465558973],"iteration":847,"passed_time":1.644834193,"remaining_time":0.2948287704},
{"learn":[0.02461833562],"iteration":848,"passed_time":1.647254308,"remaining_time":0.2929745589},
{"learn":[0.02456627972],"iteration":849,"passed_time":1.649056376,"remaining_time":0.2910099488},
{"learn":[0.02453721174],"iteration":850,"passed_time":1.650802609,"remaining_time":0.2890359444},
{"learn":[0.02450575683],"iteration":851,"passed_time":1.652614877,"remaining_time":0.2870739458},
{"learn":[0.02447443794],"iteration":852,"passed_time":1.654386731,"remaining_time":0.2851053334},
{"learn":[0.02443794665],"iteration":853,"passed_time":1.656101218,"remaining_time":0.2831273746},
{"learn":[0.02439918544],"iteration":854,"passed_time":1.657812958,"remaining_time":0.2811495659},
{"learn":[0.02437281233],"iteration":855,"passed_time":1.659654092,"remaining_time":0.2791941464},
{"learn":[0.02434514325],"iteration":856,"passed_time":1.661563691,"remaining_time":0.2772504176},
{"learn":[0.02428962195],"iteration":857,"passed_time":1.663402202,"remaining_time":0.2752950031},
{"learn":[0.02426223874],"iteration":858,"passed_time":1.665069422,"remaining_time":0.2733117445},
{"learn":[0.02422799511],"iteration":859,"passed_time":1.666593744,"remaining_time":0.2713059583},
{"learn":[0.02418631131],"iteration":860,"passed_time":1.668580934,"remaining_time":0.2693760161},
{"learn":[0.0241592766],"iteration":861,"passed_time":1.670180744,"remaining_time":0.2673839241},
{"learn":[0.02412419471],"iteration":862,"passed_time":1.671903596,"remaining_time":0.2654122742},
{"learn":[0.02409783531],"iteration":863,"passed_time":1.672920295,"remaining_time":0.2633300465},
{"learn":[0.02406106757],"iteration":864,"passed_time":1.674810726,"remaining_time":0.261386645},
{"learn":[0.02402933712],"iteration":865,"passed_time":1.676560831,"remaining_time":0.2594216528},
{"learn":[0.02399949386],"iteration":866,"passed_time":1.678257004,"remaining_time":0.2574488829},
{"learn":[0.02396146934],"iteration":867,"passed_time":1.680018237,"remaining_time":0.2554866444},
{"learn":[0.02392683945],"iteration":868,"passed_time":1.681738648,"remaining_time":0.2535187146},
{"learn":[0.02389985308],"iteration":869,"passed_time":1.683364469,"remaining_time":0.2515372195},
{"learn":[0.02387253986],"iteration":870,"passed_time":1.685039405,"remaining_time":0.2495638155},
{"learn":[0.02384237765],"iteration":871,"passed_time":1.686824388,"remaining_time":0.2476072496},
{"learn":[0.02380653871],"iteration":872,"passed_time":1.688747778,"remaining_time":0.2456712117},
{"learn":[0.02377622769],"iteration":873,"passed_time":1.690678863,"remaining_time":0.243736312},
{"learn":[0.02374470122],"iteration":874,"passed_time":1.692603335,"remaining_time":0.2418004765},
{"learn":[0.02371809953],"iteration":875,"passed_time":1.694392136,"remaining_time":0.2398454621},
{"learn":[0.02368438431],"iteration":876,"passed_time":1.696411897,"remaining_time":0.2379232193},
{"learn":[0.02366244473],"iteration":877,"passed_time":1.697996976,"remaining_time":0.2359403543},
{"learn":[0.02364414909],"iteration":878,"passed_time":1.699757127,"remaining_time":0.2339824942},
{"learn":[0.02361495089],"iteration":879,"passed_time":1.701383005,"remaining_time":0.2320067735},
{"learn":[0.0235940821],"iteration":880,"passed_time":1.703075181,"remaining_time":0.2300408019},
{"learn":[0.02356915011],"iteration":881,"passed_time":1.705045813,"remaining_time":0.2281127052},
{"learn":[0.0235368399],"iteration":882,"passed_time":1.706675438,"remaining_time":0.2261393276},
{"learn":[0.02349367846],"iteration":883,"passed_time":1.708692771,"remaining_time":0.2242176034},
{"learn":[0.02345994267],"iteration":884,"passed_time":1.710404346,"remaining_time":0.2222559319},
{"learn":[0.02343871352],"iteration":885,"passed_time":1.712198262,"remaining_time":0.2203054197},
{"learn":[0.02340572961],"iteration":886,"passed_time":1.714035787,"remaining_time":0.2183608161},
{"learn":[0.02337392281],"iteration":887,"passed_time":1.715798086,"remaining_time":0.2164069658},
{"learn":[0.02334750863],"iteration":888,"passed_time":1.717645421,"remaining_time":0.2144641639},
{"learn":[0.02330311558],"iteration":889,"passed_time":1.719474777,"remaining_time":0.2125193544},
{"learn":[0.02327810944],"iteration":890,"passed_time":1.721382342,"remaining_time":0.2105843718},
{"learn":[0.02324878864],"iteration":891,"passed_time":1.723200934,"remaining_time":0.2086386781},
{"learn":[0.02321741155],"iteration":892,"passed_time":1.724953364,"remaining_time":0.2066853415},
{"learn":[0.02318647682],"iteration":893,"passed_time":1.726624813,"remaining_time":0.2047228525},
{"learn":[0.02315944478],"iteration":894,"passed_time":1.728277115,"remaining_time":0.2027587677},
{"learn":[0.02312436181],"iteration":895,"passed_time":1.729982562,"remaining_time":0.2008015473},
{"learn":[0.02309774111],"iteration":896,"passed_time":1.731723059,"remaining_time":0.1988489131},
{"learn":[0.02307482312],"iteration":897,"passed_time":1.733724266,"remaining_time":0.1969263643},
{"learn":[0.02304363757],"iteration":898,"passed_time":1.735438713,"remaining_time":0.1949714238},
{"learn":[0.0230194489],"iteration":899,"passed_time":1.737255156,"remaining_time":0.1930283506},
{"learn":[0.02299850668],"iteration":900,"passed_time":1.739248922,"remaining_time":0.1911050425},
{"learn":[0.02298934924],"iteration":901,"passed_time":1.740892685,"remaining_time":0.1891435512},
{"learn":[0.02296531726],"iteration":902,"passed_time":1.742411613,"remaining_time":0.1871693538},
{"learn":[0.02294553615],"iteration":903,"passed_time":1.743493209,"remaining_time":0.1851497213},
{"learn":[0.02291820641],"iteration":904,"passed_time":1.745243397,"remaining_time":0.1832023455},
{"learn":[0.02288679742],"iteration":905,"passed_time":1.746821037,"remaining_time":0.1812375027},
{"learn":[0.02286163878],"iteration":906,"passed_time":1.748551448,"remaining_time":0.1792891782},
{"learn":[0.02283237837],"iteration":907,"passed_time":1.750259311,"remaining_time":0.1773390491},
{"learn":[0.02280481855],"iteration":908,"passed_time":1.752045701,"remaining_time":0.1753973144},
{"learn":[0.0227752111],"iteration":909,"passed_time":1.753941,"remaining_time":0.1734666923},
{"learn":[0.02273849745],"iteration":910,"passed_time":1.755667098,"remaining_time":0.1715196177},
{"learn":[0.02271240139],"iteration":911,"passed_time":1.757237841,"remaining_time":0.1695580373},
{"learn":[0.02267927319],"iteration":912,"passed_time":1.759016414,"remaining_time":0.1676171172},
{"learn":[0.02265371427],"iteration":913,"passed_time":1.76073616,"remaining_time":0.1656710173},
{"learn":[0.02263306772],"iteration":914,"passed_time":1.76245813,"remaining_time":0.1637256186},
{"learn":[0.02260984948],"iteration":915,"passed_time":1.76420305,"remaining_time":0.1617828125},
{"learn":[0.02259091778],"iteration":916,"passed_time":1.765827496,"remaining_time":0.1598295335},
{"learn":[0.02257096545],"iteration":917,"passed_time":1.767539156,"remaining_time":0.1578847612},
{"learn":[0.02254388879],"iteration":918,"passed_time":1.769360599,"remaining_time":0.1559501725},
{"learn":[0.02251295218],"iteration":919,"passed_time":1.771402387,"remaining_time":0.1540349902},
{"learn":[0.02249672328],"iteration":920,"passed_time":1.773249869,"remaining_time":0.1521028661},
{"learn":[0.02247039857],"iteration":921,"passed_time":1.775024932,"remaining_time":0.150164799},
{"learn":[0.02244181978],"iteration":922,"passed_time":1.776834922,"remaining_time":0.1482299989},
{"learn":[0.02241836787],"iteration":923,"passed_time":1.778639176,"remaining_time":0.1462949971},
{"learn":[0.02238911565],"iteration":924,"passed_time":1.780316621,"remaining_time":0.1443499963},
{"learn":[0.02235597207],"iteration":925,"passed_time":1.782082552,"remaining_time":0.1424126446},
{"learn":[0.02233006045],"iteration":926,"passed_time":1.783812475,"remaining_time":0.1404728271},
{"learn":[0.02231359357],"iteration":927,"passed_time":1.78561823,"remaining_time":0.1385393454},
{"learn":[0.02228095942],"iteration":928,"passed_time":1.787298315,"remaining_time":0.1365965343},
{"learn":[0.02222791742],"iteration":929,"passed_time":1.788971656,"remaining_time":0.1346537806},
{"learn":[0.02221270886],"iteration":930,"passed_time":1.790721538,"remaining_time":0.1327172783},
{"learn":[0.0221885427],"iteration":931,"passed_time":1.79236925,"remaining_time":0.1307737221},
{"learn":[0.02216366417],"iteration":932,"passed_time":1.794104282,"remaining_time":0.1288370706},
{"learn":[0.02212373088],"iteration":933,"passed_time":1.795795049,"remaining_time":0.1268977229},
{"learn":[0.02209156987],"iteration":934,"passed_time":1.797503415,"remaining_time":0.1249601304},
{"learn":[0.02205956454],"iteration":935,"passed_time":1.799293885,"remaining_time":0.1230286417},
{"learn":[0.02203848236],"iteration":936,"passed_time":1.801148669,"remaining_time":0.1211017781},
{"learn":[0.02201288651],"iteration":937,"passed_time":1.802844087,"remaining_time":0.1191645345},
{"learn":[0.02198221245],"iteration":938,"passed_time":1.804569953,"remaining_time":0.1172297839},
{"learn":[0.02195254971],"iteration":939,"passed_time":1.806337177,"remaining_time":0.1152981177},
{"learn":[0.02192042047],"iteration":940,"passed_time":1.808062137,"remaining_time":0.113364151},
{"learn":[0.02187457729],"iteration":941,"passed_time":1.809809265,"remaining_time":0.111431993},
{"learn":[0.02185499559],"iteration":942,"passed_time":1.810827767,"remaining_time":0.1094561853},
{"learn":[0.02183810774],"iteration":943,"passed_time":1.812600372,"remaining_time":0.1075271407},
{"learn":[0.02182389075],"iteration":944,"passed_time":1.814269172,"remaining_time":0.1055923857},
{"learn":[0.02180003419],"iteration":945,"passed_time":1.815521207,"remaining_time":0.1036344029},
{"learn":[0.02174099499],"iteration":946,"passed_time":1.817201064,"remaining_time":0.1017018547},
{"learn":[0.02171613223],"iteration":947,"passed_time":1.818914908,"remaining_time":0.09977170381},
{"learn":[0.02170115032],"iteration":948,"passed_time":1.82063116,"remaining_time":0.09784213819},
{"learn":[0.02167619115],"iteration":949,"passed_time":1.8221977,"remaining_time":0.09590514211},
{"learn":[0.02164941318],"iteration":950,"passed_time":1.823875525,"remaining_time":0.09397465901},
{"learn":[0.02162337755],"iteration":951,"passed_time":1.825654606,"remaining_time":0.09204981205},
{"learn":[0.02159512684],"iteration":952,"passed_time":1.82736431,"remaining_time":0.09012184951},
{"learn":[0.02156625548],"iteration":953,"passed_time":1.829146189,"remaining_time":0.08819782464},
{"learn":[0.02153738745],"iteration":954,"passed_time":1.830931585,"remaining_time":0.08627426319},
{"learn":[0.02151749271],"iteration":955,"passed_time":1.832519447,"remaining_time":0.08434189924},
{"learn":[0.02148527159],"iteration":956,"passed_time":1.834297205,"remaining_time":0.08241878769},
{"learn":[0.02146272928],"iteration":957,"passed_time":1.836070983,"remaining_time":0.08049580508},
{"learn":[0.0214512742],"iteration":958,"passed_time":1.837775482,"remaining_time":0.07857017181},
{"learn":[0.021429812],"iteration":959,"passed_time":1.839727861,"remaining_time":0.07665532753},
{"learn":[0.02137739894],"iteration":960,"passed_time":1.841399502,"remaining_time":0.07472901205},
{"learn":[0.02133824873],"iteration":961,"passed_time":1.84309955,"remaining_time":0.07280434814},
{"learn":[0.02132579476],"iteration":962,"passed_time":1.844805961,"remaining_time":0.07088039519},
{"learn":[0.02130847454],"iteration":963,"passed_time":1.8465156,"remaining_time":0.0689570141},
{"learn":[0.02126586049],"iteration":964,"passed_time":1.848189346,"remaining_time":0.06703277421},
{"learn":[0.02124783991],"iteration":965,"passed_time":1.849876753,"remaining_time":0.06510953375},
{"learn":[0.02122618983],"iteration":966,"passed_time":1.851488619,"remaining_time":0.06318420313},
{"learn":[0.02120989109],"iteration":967,"passed_time":1.853252726,"remaining_time":0.06126455292},
{"learn":[0.02118448803],"iteration":968,"passed_time":1.854953896,"remaining_time":0.05934321031},
{"learn":[0.02115455733],"iteration":969,"passed_time":1.856733961,"remaining_time":0.05742476168},
{"learn":[0.02113364426],"iteration":970,"passed_time":1.858649063,"remaining_time":0.05551063113},
{"learn":[0.02110677682],"iteration":971,"passed_time":1.860654792,"remaining_time":0.05359910924},
{"learn":[0.02106952964],"iteration":972,"passed_time":1.865679543,"remaining_time":0.05177116924},
{"learn":[0.02103414351],"iteration":973,"passed_time":1.867367784,"remaining_time":0.04984759999},
{"learn":[0.02101487659],"iteration":974,"passed_time":1.869219171,"remaining_time":0.04792869669},
{"learn":[0.02098886882],"iteration":975,"passed_time":1.870940968,"remaining_time":0.0460067451},
{"learn":[0.02095661903],"iteration":976,"passed_time":1.872618017,"remaining_time":0.04408414984},
{"learn":[0.02093175739],"iteration":977,"passed_time":1.874299824,"remaining_time":0.04216216374},
{"learn":[0.02089240624],"iteration":978,"passed_time":1.875985892,"remaining_time":0.04024075967},
{"learn":[0.02088178012],"iteration":979,"passed_time":1.878384192,"remaining_time":0.03833437126},
{"learn":[0.02085916276],"iteration":980,"passed_time":1.880349594,"remaining_time":0.03641859561},
{"learn":[0.02083105637],"iteration":981,"passed_time":1.882228026,"remaining_time":0.03450112471},
{"learn":[0.02080555037],"iteration":982,"passed_time":1.884003928,"remaining_time":0.0325819601},
{"learn":[0.02077838657],"iteration":983,"passed_time":1.885960611,"remaining_time":0.03066602619},
{"learn":[0.02076192819],"iteration":984,"passed_time":1.887734956,"remaining_time":0.02874723283},
{"learn":[0.02074288701],"iteration":985,"passed_time":1.889301969,"remaining_time":0.02682578861},
{"learn":[0.0207218974],"iteration":986,"passed_time":1.890867627,"remaining_time":0.02490504473},
{"learn":[0.02070099956],"iteration":987,"passed_time":1.892652014,"remaining_time":0.02298767628},
{"learn":[0.02068652027],"iteration":988,"passed_time":1.89444269,"remaining_time":0.02107064671},
{"learn":[0.0206684329],"iteration":989,"passed_time":1.896073353,"remaining_time":0.01915225609},
{"learn":[0.02062961672],"iteration":990,"passed_time":1.89786351,"remaining_time":0.01723589464},
{"learn":[0.02058352408],"iteration":991,"passed_time":1.899589616,"remaining_time":0.0153192711},
{"learn":[0.02055678955],"iteration":992,"passed_time":1.901558286,"remaining_time":0.01340474119},
{"learn":[0.02053415435],"iteration":993,"passed_time":1.903447575,"remaining_time":0.01148962319},
{"learn":[0.02051005717],"iteration":994,"passed_time":1.905312639,"remaining_time":0.009574435373},
{"learn":[0.02046845751],"iteration":995,"passed_time":1.907145089,"remaining_time":0.007659217225},
{"learn":[0.02044186358],"iteration":996,"passed_time":1.909326376,"remaining_time":0.005745214773},
{"learn":[0.02041471354],"iteration":997,"passed_time":1.911118704,"remaining_time":0.003829897202},
{"learn":[0.02039858023],"iteration":998,"passed_time":1.912771838,"remaining_time":0.001914686524},
{"learn":[0.02035834272],"iteration":999,"passed_time":1.914478709,"remaining_time":0}
]}